{"v":"5.7.3","fr":29.9700012207031,"ip":0,"op":150.000006109625,"w":500,"h":500,"nm":"Currency converter","ddd":0,"assets":[],"layers":[{"ddd":0,"ind":1,"ty":4,"nm":"Layer 13 Outlines - Group 1 :M :M","parent":10,"sr":1,"ks":{"o":{"a":0,"k":100,"ix":11},"r":{"a":0,"k":0,"ix":10},"p":{"a":0,"k":[222.595,237.518,0],"ix":2},"a":{"a":0,"k":[217.52,235.207,0],"ix":1},"s":{"a":0,"k":[84.375,84.375,100],"ix":6}},"ao":0,"shapes":[{"ty":"gr","it":[{"ty":"gr","it":[{"ty":"gr","it":[{"ind":0,"ty":"sh","ix":1,"ks":{"a":0,"k":{"i":[[0.162,0],[0.125,0.124],[-0.249,0.249],[0,0],[-0.249,-0.248],[0.249,-0.248],[0,0]],"o":[[-0.163,0],[-0.249,-0.25],[0,0],[0.249,-0.248],[0.249,0.25],[0,0],[-0.124,0.124]],"v":[[-1.47,2.137],[-1.921,1.952],[-1.921,1.051],[1.019,-1.889],[1.921,-1.889],[1.921,-0.989],[-1.02,1.952]],"c":true},"ix":2},"nm":"Path 1","mn":"ADBE Vector Shape - Group","hd":false},{"ty":"fl","c":{"a":0,"k":[0,0.282352954149,0.549019634724,1],"ix":4,"x":"var $bm_rt;\ntry {\n    $bm_rt = thisComp.layer('Controller').effect('Color')('ADBE Color Control-0001');\n} catch (e) {\n    $bm_rt = value;\n}"},"o":{"a":0,"k":100,"ix":5},"r":1,"bm":0,"nm":"Fill 1","mn":"ADBE Vector Graphic - Fill","hd":false},{"ty":"tr","p":{"a":0,"k":[24.309,51.561],"ix":2},"a":{"a":0,"k":[0,0],"ix":1},"s":{"a":0,"k":[100,100],"ix":3},"r":{"a":0,"k":0,"ix":6},"o":{"a":0,"k":100,"ix":7},"sk":{"a":0,"k":0,"ix":4},"sa":{"a":0,"k":0,"ix":5},"nm":"Transform"}],"nm":"Group 1","np":2,"cix":2,"bm":0,"ix":1,"mn":"ADBE Vector Group","hd":false},{"ty":"tr","p":{"a":0,"k":[211.09,344.778],"ix":2},"a":{"a":0,"k":[24.309,51.592],"ix":1},"s":{"a":0,"k":[490,490],"ix":3},"r":{"a":0,"k":0,"ix":6},"o":{"a":0,"k":100,"ix":7},"sk":{"a":0,"k":0,"ix":4},"sa":{"a":0,"k":0,"ix":5},"nm":"Transform"}],"nm":"Layer 13 Outlines - Group 1","np":1,"cix":2,"bm":0,"ix":1,"mn":"ADBE Vector Group","hd":false},{"ty":"gr","it":[{"ty":"gr","it":[{"ind":0,"ty":"sh","ix":1,"ks":{"a":0,"k":{"i":[[0.162,0],[0.125,0.124],[0,0],[-0.249,0.25],[-0.248,-0.248],[0,0],[0.249,-0.25]],"o":[[-0.163,0],[0,0],[-0.249,-0.248],[0.249,-0.248],[0,0],[0.249,0.249],[-0.124,0.124]],"v":[[1.471,2.137],[1.02,1.952],[-1.921,-0.989],[-1.921,-1.889],[-1.019,-1.889],[1.921,1.051],[1.921,1.952]],"c":true},"ix":2},"nm":"Path 1","mn":"ADBE Vector Shape - Group","hd":false},{"ty":"fl","c":{"a":0,"k":[0,0.282352954149,0.549019634724,1],"ix":4,"x":"var $bm_rt;\ntry {\n    $bm_rt = thisComp.layer('Controller')('Effects')('Color')('ADBE Color Control-0001');\n} catch (e) {\n    $bm_rt = value;\n}"},"o":{"a":0,"k":100,"ix":5},"r":1,"bm":0,"nm":"Fill 1","mn":"ADBE Vector Graphic - Fill","hd":false},{"ty":"tr","p":{"a":0,"k":[24.309,51.561],"ix":2},"a":{"a":0,"k":[0,0],"ix":1},"s":{"a":0,"k":[100,100],"ix":3},"r":{"a":0,"k":0,"ix":6},"o":{"a":0,"k":100,"ix":7},"sk":{"a":0,"k":0,"ix":4},"sa":{"a":0,"k":0,"ix":5},"nm":"Transform"}],"nm":"Group 2","np":2,"cix":2,"bm":0,"ix":1,"mn":"ADBE Vector Group","hd":false},{"ty":"tr","p":{"a":0,"k":[211.087,344.778],"ix":2},"a":{"a":0,"k":[24.309,51.592],"ix":1},"s":{"a":0,"k":[490,490],"ix":3},"r":{"a":0,"k":0,"ix":6},"o":{"a":0,"k":100,"ix":7},"sk":{"a":0,"k":0,"ix":4},"sa":{"a":0,"k":0,"ix":5},"nm":"Transform"}],"nm":"Layer 13 Outlines - Group 2","np":1,"cix":2,"bm":0,"ix":2,"mn":"ADBE Vector Group","hd":false},{"ty":"tr","p":{"a":0,"k":[203.883,362.33],"ix":2},"a":{"a":0,"k":[211.089,344.778],"ix":1},"s":{"a":1,"k":[{"i":{"x":[0.6,0.6],"y":[1,1]},"o":{"x":[0.4,0.4],"y":[0,0]},"t":54,"s":[0,0]},{"i":{"x":[0.6,0.6],"y":[1,1]},"o":{"x":[0.4,0.4],"y":[0,0]},"t":69,"s":[118.519,118.519]},{"i":{"x":[0.833,0.833],"y":[1,1]},"o":{"x":[0.167,0.167],"y":[0,0]},"t":84,"s":[0,0]},{"i":{"x":[0.6,0.6],"y":[1,1]},"o":{"x":[0.4,0.4],"y":[0,0]},"t":120,"s":[0,0]},{"i":{"x":[0.6,0.6],"y":[1,1]},"o":{"x":[0.4,0.4],"y":[0,0]},"t":135,"s":[118.519,118.519]},{"t":150.000006109625,"s":[0,0]}],"ix":3},"r":{"a":0,"k":0,"ix":6},"o":{"a":0,"k":100,"ix":7},"sk":{"a":0,"k":0,"ix":4},"sa":{"a":0,"k":0,"ix":5},"nm":"Transform"}],"nm":"Layer 13 Outlines - Group 1 :M","np":2,"cix":2,"bm":0,"ix":1,"mn":"ADBE Vector Group","hd":false},{"ty":"gr","it":[{"ty":"gr","it":[{"ty":"gr","it":[{"ind":0,"ty":"sh","ix":1,"ks":{"a":0,"k":{"i":[[0.162,0],[0.124,0.125],[-0.249,0.249],[0,0],[-0.249,-0.249],[0.249,-0.248],[0,0]],"o":[[-0.163,0],[-0.249,-0.249],[0,0],[0.249,-0.249],[0.249,0.249],[0,0],[-0.124,0.125]],"v":[[-1.47,2.138],[-1.921,1.951],[-1.921,1.051],[1.019,-1.889],[1.921,-1.889],[1.921,-0.989],[-1.02,1.951]],"c":true},"ix":2},"nm":"Path 1","mn":"ADBE Vector Shape - Group","hd":false},{"ty":"fl","c":{"a":0,"k":[0,0.282352954149,0.549019634724,1],"ix":4,"x":"var $bm_rt;\ntry {\n    $bm_rt = thisComp.layer('Controller')('Effects')('Color')('ADBE Color Control-0001');\n} catch (e) {\n    $bm_rt = value;\n}"},"o":{"a":0,"k":100,"ix":5},"r":1,"bm":0,"nm":"Fill 1","mn":"ADBE Vector Graphic - Fill","hd":false},{"ty":"tr","p":{"a":0,"k":[10.581,7.781],"ix":2},"a":{"a":0,"k":[0,0],"ix":1},"s":{"a":0,"k":[100,100],"ix":3},"r":{"a":0,"k":0,"ix":6},"o":{"a":0,"k":100,"ix":7},"sk":{"a":0,"k":0,"ix":4},"sa":{"a":0,"k":0,"ix":5},"nm":"Transform"}],"nm":"Group 3","np":2,"cix":2,"bm":0,"ix":1,"mn":"ADBE Vector Group","hd":false},{"ty":"tr","p":{"a":0,"k":[143.821,130.258],"ix":2},"a":{"a":0,"k":[10.581,7.813],"ix":1},"s":{"a":0,"k":[490,490],"ix":3},"r":{"a":0,"k":0,"ix":6},"o":{"a":0,"k":100,"ix":7},"sk":{"a":0,"k":0,"ix":4},"sa":{"a":0,"k":0,"ix":5},"nm":"Transform"}],"nm":"Layer 13 Outlines - Group 3","np":1,"cix":2,"bm":0,"ix":1,"mn":"ADBE Vector Group","hd":false},{"ty":"gr","it":[{"ty":"gr","it":[{"ind":0,"ty":"sh","ix":1,"ks":{"a":0,"k":{"i":[[0.163,0],[0.124,0.125],[0,0],[-0.249,0.249],[-0.249,-0.249],[0,0],[0.249,-0.249]],"o":[[-0.162,0],[0,0],[-0.249,-0.248],[0.249,-0.249],[0,0],[0.249,0.249],[-0.124,0.125]],"v":[[1.47,2.138],[1.02,1.951],[-1.921,-0.989],[-1.921,-1.889],[-1.019,-1.889],[1.921,1.051],[1.921,1.951]],"c":true},"ix":2},"nm":"Path 1","mn":"ADBE Vector Shape - Group","hd":false},{"ty":"fl","c":{"a":0,"k":[0,0.282352954149,0.549019634724,1],"ix":4,"x":"var $bm_rt;\ntry {\n    $bm_rt = thisComp.layer('Controller')('Effects')('Color')('ADBE Color Control-0001');\n} catch (e) {\n    $bm_rt = value;\n}"},"o":{"a":0,"k":100,"ix":5},"r":1,"bm":0,"nm":"Fill 1","mn":"ADBE Vector Graphic - Fill","hd":false},{"ty":"tr","p":{"a":0,"k":[10.58,7.781],"ix":2},"a":{"a":0,"k":[0,0],"ix":1},"s":{"a":0,"k":[100,100],"ix":3},"r":{"a":0,"k":0,"ix":6},"o":{"a":0,"k":100,"ix":7},"sk":{"a":0,"k":0,"ix":4},"sa":{"a":0,"k":0,"ix":5},"nm":"Transform"}],"nm":"Group 4","np":2,"cix":2,"bm":0,"ix":1,"mn":"ADBE Vector Group","hd":false},{"ty":"tr","p":{"a":0,"k":[143.818,130.258],"ix":2},"a":{"a":0,"k":[10.58,7.813],"ix":1},"s":{"a":0,"k":[490,490],"ix":3},"r":{"a":0,"k":0,"ix":6},"o":{"a":0,"k":100,"ix":7},"sk":{"a":0,"k":0,"ix":4},"sa":{"a":0,"k":0,"ix":5},"nm":"Transform"}],"nm":"Layer 13 Outlines - Group 4","np":1,"cix":2,"bm":0,"ix":2,"mn":"ADBE Vector Group","hd":false},{"ty":"tr","p":{"a":0,"k":[124.156,108.083],"ix":2},"a":{"a":0,"k":[143.819,130.258],"ix":1},"s":{"a":1,"k":[{"i":{"x":[0.6,0.6],"y":[1,1]},"o":{"x":[0.4,0.4],"y":[0,0]},"t":48,"s":[0,0]},{"i":{"x":[0.6,0.6],"y":[1,1]},"o":{"x":[0.4,0.4],"y":[0,0]},"t":63,"s":[118.519,118.519]},{"i":{"x":[0.833,0.833],"y":[1,1]},"o":{"x":[0.167,0.167],"y":[0,0]},"t":78,"s":[0,0]},{"i":{"x":[0.6,0.6],"y":[1,1]},"o":{"x":[0.4,0.4],"y":[0,0]},"t":123,"s":[0,0]},{"i":{"x":[0.6,0.6],"y":[1,1]},"o":{"x":[0.4,0.4],"y":[0,0]},"t":138,"s":[118.519,118.519]},{"t":150.000006109625,"s":[0,0]}],"ix":3},"r":{"a":0,"k":0,"ix":6},"o":{"a":0,"k":100,"ix":7},"sk":{"a":0,"k":0,"ix":4},"sa":{"a":0,"k":0,"ix":5},"nm":"Transform"}],"nm":"Layer 13 Outlines - Group 3 :M","np":2,"cix":2,"bm":0,"ix":2,"mn":"ADBE Vector Group","hd":false},{"ty":"gr","it":[{"ty":"gr","it":[{"ty":"gr","it":[{"ind":0,"ty":"sh","ix":1,"ks":{"a":0,"k":{"i":[[0.163,0],[0.124,0.125],[-0.249,0.248],[0,0],[-0.249,-0.249],[0.249,-0.249],[0,0]],"o":[[-0.162,0],[-0.249,-0.249],[0,0],[0.248,-0.249],[0.249,0.249],[0,0],[-0.124,0.125]],"v":[[-1.471,2.138],[-1.921,1.951],[-1.921,1.051],[1.019,-1.889],[1.921,-1.889],[1.921,-0.989],[-1.02,1.951]],"c":true},"ix":2},"nm":"Path 1","mn":"ADBE Vector Shape - Group","hd":false},{"ty":"fl","c":{"a":0,"k":[0,0.282352954149,0.549019634724,1],"ix":4,"x":"var $bm_rt;\ntry {\n    $bm_rt = thisComp.layer('Controller')('Effects')('Color')('ADBE Color Control-0001');\n} catch (e) {\n    $bm_rt = value;\n}"},"o":{"a":0,"k":100,"ix":5},"r":1,"bm":0,"nm":"Fill 1","mn":"ADBE Vector Graphic - Fill","hd":false},{"ty":"tr","p":{"a":0,"k":[42.734,15.866],"ix":2},"a":{"a":0,"k":[0,0],"ix":1},"s":{"a":0,"k":[100,100],"ix":3},"r":{"a":0,"k":0,"ix":6},"o":{"a":0,"k":100,"ix":7},"sk":{"a":0,"k":0,"ix":4},"sa":{"a":0,"k":0,"ix":5},"nm":"Transform"}],"nm":"Group 5","np":2,"cix":2,"bm":0,"ix":1,"mn":"ADBE Vector Group","hd":false},{"ty":"tr","p":{"a":0,"k":[301.372,169.874],"ix":2},"a":{"a":0,"k":[42.734,15.897],"ix":1},"s":{"a":0,"k":[490,490],"ix":3},"r":{"a":0,"k":0,"ix":6},"o":{"a":0,"k":100,"ix":7},"sk":{"a":0,"k":0,"ix":4},"sa":{"a":0,"k":0,"ix":5},"nm":"Transform"}],"nm":"Layer 13 Outlines - Group 5","np":1,"cix":2,"bm":0,"ix":1,"mn":"ADBE Vector Group","hd":false},{"ty":"gr","it":[{"ty":"gr","it":[{"ind":0,"ty":"sh","ix":1,"ks":{"a":0,"k":{"i":[[0.163,0],[0.124,0.125],[0,0],[-0.249,0.249],[-0.249,-0.249],[0,0],[0.249,-0.249]],"o":[[-0.162,0],[0,0],[-0.249,-0.249],[0.249,-0.249],[0,0],[0.249,0.248],[-0.125,0.125]],"v":[[1.47,2.138],[1.02,1.951],[-1.921,-0.989],[-1.921,-1.889],[-1.019,-1.889],[1.921,1.051],[1.921,1.951]],"c":true},"ix":2},"nm":"Path 1","mn":"ADBE Vector Shape - Group","hd":false},{"ty":"fl","c":{"a":0,"k":[0,0.282352954149,0.549019634724,1],"ix":4,"x":"var $bm_rt;\ntry {\n    $bm_rt = thisComp.layer('Controller')('Effects')('Color')('ADBE Color Control-0001');\n} catch (e) {\n    $bm_rt = value;\n}"},"o":{"a":0,"k":100,"ix":5},"r":1,"bm":0,"nm":"Fill 1","mn":"ADBE Vector Graphic - Fill","hd":false},{"ty":"tr","p":{"a":0,"k":[42.733,15.866],"ix":2},"a":{"a":0,"k":[0,0],"ix":1},"s":{"a":0,"k":[100,100],"ix":3},"r":{"a":0,"k":0,"ix":6},"o":{"a":0,"k":100,"ix":7},"sk":{"a":0,"k":0,"ix":4},"sa":{"a":0,"k":0,"ix":5},"nm":"Transform"}],"nm":"Group 6","np":2,"cix":2,"bm":0,"ix":1,"mn":"ADBE Vector Group","hd":false},{"ty":"tr","p":{"a":0,"k":[301.369,169.874],"ix":2},"a":{"a":0,"k":[42.733,15.897],"ix":1},"s":{"a":0,"k":[490,490],"ix":3},"r":{"a":0,"k":0,"ix":6},"o":{"a":0,"k":100,"ix":7},"sk":{"a":0,"k":0,"ix":4},"sa":{"a":0,"k":0,"ix":5},"nm":"Transform"}],"nm":"Layer 13 Outlines - Group 6","np":1,"cix":2,"bm":0,"ix":2,"mn":"ADBE Vector Group","hd":false},{"ty":"tr","p":{"a":0,"k":[310.883,155.036],"ix":2},"a":{"a":0,"k":[301.37,169.874],"ix":1},"s":{"a":1,"k":[{"i":{"x":[0.6,0.6],"y":[1,1]},"o":{"x":[0.4,0.4],"y":[0,0]},"t":51,"s":[0,0]},{"i":{"x":[0.6,0.6],"y":[1,1]},"o":{"x":[0.4,0.4],"y":[0,0]},"t":66,"s":[118.519,118.519]},{"i":{"x":[0.833,0.833],"y":[1,1]},"o":{"x":[0.167,0.167],"y":[0,0]},"t":81,"s":[0,0]},{"i":{"x":[0.6,0.6],"y":[1,1]},"o":{"x":[0.4,0.4],"y":[0,0]},"t":127,"s":[0,0]},{"i":{"x":[0.6,0.6],"y":[1,1]},"o":{"x":[0.4,0.4],"y":[0,0]},"t":142,"s":[118.519,118.519]},{"t":150.000006109625,"s":[0,0]}],"ix":3},"r":{"a":0,"k":0,"ix":6},"o":{"a":0,"k":100,"ix":7},"sk":{"a":0,"k":0,"ix":4},"sa":{"a":0,"k":0,"ix":5},"nm":"Transform"}],"nm":"Layer 13 Outlines - Group 5 :M","np":2,"cix":2,"bm":0,"ix":3,"mn":"ADBE Vector Group","hd":false}],"ip":0,"op":150.000006109625,"st":0,"bm":0},{"ddd":0,"ind":2,"ty":4,"nm":"Layer 13 Outlines - Group 7 :M","parent":3,"sr":1,"ks":{"o":{"a":0,"k":100,"ix":11},"r":{"a":0,"k":0,"ix":10},"p":{"a":0,"k":[84.149,-67.223,0],"ix":2},"a":{"a":0,"k":[339.506,158.67,0],"ix":1},"s":{"a":1,"k":[{"i":{"x":[0.6,0.6,0.6],"y":[1,1,1]},"o":{"x":[0.4,0.4,0.4],"y":[0,0,0]},"t":12,"s":[100,100,100]},{"i":{"x":[0.6,0.6,0.6],"y":[1,1,1]},"o":{"x":[0.4,0.4,0.4],"y":[0,0,0]},"t":27,"s":[80,80,100]},{"i":{"x":[0.833,0.833,0.833],"y":[1,1,1]},"o":{"x":[0.167,0.167,0.167],"y":[0,0,0]},"t":42,"s":[100,100,100]},{"i":{"x":[0.6,0.6,0.6],"y":[1,1,1]},"o":{"x":[0.4,0.4,0.4],"y":[0,0,0]},"t":86,"s":[100,100,100]},{"i":{"x":[0.6,0.6,0.6],"y":[1,1,1]},"o":{"x":[0.4,0.4,0.4],"y":[0,0,0]},"t":101,"s":[80,80,100]},{"t":116.000004724777,"s":[100,100,100]}],"ix":6}},"ao":0,"shapes":[{"ty":"gr","it":[{"ty":"gr","it":[{"ind":0,"ty":"sh","ix":1,"ks":{"a":0,"k":{"i":[[0.17,0],[0,0],[0.119,0.12],[0,0],[-0.099,0.237],[-0.258,0],[0,0],[0.132,0.049],[-0.055,0.303],[-0.309,0],[-2.491,-3.546],[0.287,-0.202],[0.202,0.288],[5.834,0.635],[0,-7.248],[0.351,0],[0,0],[0,0],[0,0],[0,0],[0.028,0.329],[0.778,2.025],[-0.329,0.126],[-0.125,-0.328],[-0.109,-0.676],[0,0],[-0.097,-0.239],[0.182,-0.182],[0,0]],"o":[[0,0],[-0.169,0],[0,0],[-0.181,-0.182],[0.098,-0.239],[0,0],[-0.592,-8.866],[-0.29,-0.106],[0.054,-0.304],[9.92,0],[0.202,0.289],[-0.29,0.203],[-2.85,-4.058],[4.238,2.184],[0,0.351],[0,0],[0,0],[0,0],[0,0],[-0.331,0],[-0.002,-0.016],[-0.126,-0.329],[0.33,-0.124],[0.557,1.451],[0,0],[0.257,0],[0.099,0.237],[0,0],[-0.12,0.12]],"v":[[5.153,11.417],[5.153,11.417],[4.702,11.231],[-1.904,4.626],[-2.041,3.932],[-1.451,3.538],[1.545,3.538],[-11.982,-10.183],[-12.39,-10.893],[-11.764,-11.417],[5.7,-3.643],[5.545,-2.755],[4.657,-2.91],[-8.416,-9.969],[2.839,4.175],[2.204,4.812],[0.087,4.812],[5.153,9.88],[10.221,4.812],[8.104,4.812],[7.468,4.229],[6.553,0.663],[6.919,-0.16],[7.742,0.206],[8.661,3.538],[11.758,3.538],[12.346,3.932],[12.209,4.626],[5.604,11.231]],"c":true},"ix":2},"nm":"Path 1","mn":"ADBE Vector Shape - Group","hd":false},{"ty":"fl","c":{"a":0,"k":[0,0.282352954149,0.549019634724,1],"ix":4,"x":"var $bm_rt;\ntry {\n    $bm_rt = thisComp.layer('Controller')('Effects')('Color')('ADBE Color Control-0001');\n} catch (e) {\n    $bm_rt = value;\n}"},"o":{"a":0,"k":100,"ix":5},"r":1,"bm":0,"nm":"Fill 1","mn":"ADBE Vector Graphic - Fill","hd":false},{"ty":"tr","p":{"a":0,"k":[47.938,15.585],"ix":2},"a":{"a":0,"k":[0,0],"ix":1},"s":{"a":0,"k":[100,100],"ix":3},"r":{"a":0,"k":0,"ix":6},"o":{"a":0,"k":100,"ix":7},"sk":{"a":0,"k":0,"ix":4},"sa":{"a":0,"k":0,"ix":5},"nm":"Transform"}],"nm":"Group 7","np":2,"cix":2,"bm":0,"ix":1,"mn":"ADBE Vector Group","hd":false},{"ty":"tr","p":{"a":0,"k":[326.857,168.342],"ix":2},"a":{"a":0,"k":[47.935,15.585],"ix":1},"s":{"a":0,"k":[490,490],"ix":3},"r":{"a":0,"k":0,"ix":6},"o":{"a":0,"k":100,"ix":7},"sk":{"a":0,"k":0,"ix":4},"sa":{"a":0,"k":0,"ix":5},"nm":"Transform"}],"nm":"Layer 13 Outlines - Group 7","np":1,"cix":2,"bm":0,"ix":1,"mn":"ADBE Vector Group","hd":false},{"ty":"gr","it":[{"ty":"gr","it":[{"ind":0,"ty":"sh","ix":1,"ks":{"a":0,"k":{"i":[[0,0],[0,-9.835],[0,0],[0,0]],"o":[[0,0],[0,0],[0,0],[3.268,-18.768]],"v":[[-10.092,-10.781],[3.875,4.174],[0.219,4.174],[6.824,10.781]],"c":true},"ix":2},"nm":"Path 1","mn":"ADBE Vector Shape - Group","hd":false},{"ty":"fl","c":{"a":0,"k":[1,0.835294127464,0.309803932905,1],"ix":4,"x":"var $bm_rt;\ntry {\n    $bm_rt = thisComp.layer('Controller').effect('Color 2')('ADBE Color Control-0001');\n} catch (e) {\n    $bm_rt = value;\n}"},"o":{"a":0,"k":100,"ix":5},"r":1,"bm":0,"nm":"Fill 1","mn":"ADBE Vector Graphic - Fill","hd":false},{"ty":"tr","p":{"a":0,"k":[46.266,15.585],"ix":2},"a":{"a":0,"k":[0,0],"ix":1},"s":{"a":0,"k":[100,100],"ix":3},"r":{"a":0,"k":0,"ix":6},"o":{"a":0,"k":100,"ix":7},"sk":{"a":0,"k":0,"ix":4},"sa":{"a":0,"k":0,"ix":5},"nm":"Transform"}],"nm":"Group 9","np":2,"cix":2,"bm":0,"ix":1,"mn":"ADBE Vector Group","hd":false},{"ty":"tr","p":{"a":0,"k":[311.55,168.343],"ix":2},"a":{"a":0,"k":[44.811,15.585],"ix":1},"s":{"a":0,"k":[490,490],"ix":3},"r":{"a":0,"k":0,"ix":6},"o":{"a":0,"k":100,"ix":7},"sk":{"a":0,"k":0,"ix":4},"sa":{"a":0,"k":0,"ix":5},"nm":"Transform"}],"nm":"Layer 13 Outlines - Group 9","np":1,"cix":2,"bm":0,"ix":2,"mn":"ADBE Vector Group","hd":false},{"ty":"gr","it":[{"ty":"gr","it":[{"ind":0,"ty":"sh","ix":1,"ks":{"a":0,"k":{"i":[[0,0],[18.635,0],[3.267,-18.767],[0,0]],"o":[[0,0],[0,0],[0,0],[0,0]],"v":[[8.106,4.174],[-11.761,-10.781],[5.155,10.781],[11.761,4.174]],"c":true},"ix":2},"nm":"Path 1","mn":"ADBE Vector Shape - Group","hd":false},{"ty":"fl","c":{"a":0,"k":[0.937254905701,0.521568655968,0.133333340287,1],"ix":4,"x":"var $bm_rt;\ntry {\n    $bm_rt = thisComp.layer('Controller').effect('Color 3')('ADBE Color Control-0001');\n} catch (e) {\n    $bm_rt = value;\n}"},"o":{"a":0,"k":100,"ix":5},"r":1,"bm":0,"nm":"Fill 1","mn":"ADBE Vector Graphic - Fill","hd":false},{"ty":"tr","p":{"a":0,"k":[47.935,15.585],"ix":2},"a":{"a":0,"k":[0,0],"ix":1},"s":{"a":0,"k":[100,100],"ix":3},"r":{"a":0,"k":0,"ix":6},"o":{"a":0,"k":100,"ix":7},"sk":{"a":0,"k":0,"ix":4},"sa":{"a":0,"k":0,"ix":5},"nm":"Transform"}],"nm":"Group 12","np":2,"cix":2,"bm":0,"ix":1,"mn":"ADBE Vector Group","hd":false},{"ty":"tr","p":{"a":0,"k":[326.858,168.342],"ix":2},"a":{"a":0,"k":[47.935,15.585],"ix":1},"s":{"a":0,"k":[490,490],"ix":3},"r":{"a":0,"k":0,"ix":6},"o":{"a":0,"k":100,"ix":7},"sk":{"a":0,"k":0,"ix":4},"sa":{"a":0,"k":0,"ix":5},"nm":"Transform"}],"nm":"Layer 13 Outlines - Group 112","np":1,"cix":2,"bm":0,"ix":3,"mn":"ADBE Vector Group","hd":false}],"ip":0,"op":150.000006109625,"st":0,"bm":0},{"ddd":0,"ind":3,"ty":4,"nm":"Shape Layer 3","parent":10,"sr":1,"ks":{"o":{"a":0,"k":100,"ix":11},"r":{"a":0,"k":0,"ix":10},"p":{"a":1,"k":[{"i":{"x":0.6,"y":1},"o":{"x":0.4,"y":0},"t":0,"s":[273.214,200.893,0],"to":[2.108,-1.736,0],"ti":[0,0,0]},{"i":{"x":0.6,"y":1},"o":{"x":0.4,"y":0},"t":27,"s":[285.863,190.476,0],"to":[0,0,0],"ti":[2.108,-1.736,0]},{"i":{"x":0.6,"y":0.6},"o":{"x":0.4,"y":0.4},"t":54,"s":[273.214,200.893,0],"to":[0,0,0],"ti":[0,0,0]},{"i":{"x":0.6,"y":1},"o":{"x":0.4,"y":0},"t":74,"s":[273.214,200.893,0],"to":[2.108,-1.736,0],"ti":[0,0,0]},{"i":{"x":0.6,"y":1},"o":{"x":0.4,"y":0},"t":101,"s":[285.863,190.476,0],"to":[0,0,0],"ti":[2.108,-1.736,0]},{"t":128.000005213547,"s":[273.214,200.893,0]}],"ix":2},"a":{"a":0,"k":[17.857,-25,0],"ix":1},"s":{"a":0,"k":[100,100,100],"ix":6}},"ao":0,"shapes":[{"ty":"gr","it":[{"d":1,"ty":"el","s":{"a":0,"k":[158.929,158.929],"ix":2},"p":{"a":0,"k":[0,0],"ix":3},"nm":"Ellipse Path 1","mn":"ADBE Vector Shape - Ellipse","hd":false},{"ty":"tr","p":{"a":0,"k":[17.857,-25],"ix":2},"a":{"a":0,"k":[0,0],"ix":1},"s":{"a":0,"k":[100,100],"ix":3},"r":{"a":0,"k":0,"ix":6},"o":{"a":0,"k":100,"ix":7},"sk":{"a":0,"k":0,"ix":4},"sa":{"a":0,"k":0,"ix":5},"nm":"Transform"}],"nm":"Ellipse 1","np":3,"cix":2,"bm":0,"ix":1,"mn":"ADBE Vector Group","hd":false}],"ip":0,"op":150.000006109625,"st":0,"bm":0},{"ddd":0,"ind":4,"ty":4,"nm":"Layer 13 Outlines - Group 8 :M","parent":5,"sr":1,"ks":{"o":{"a":0,"k":100,"ix":11},"r":{"a":0,"k":0,"ix":10},"p":{"a":0,"k":[-47.518,18.694,0],"ix":2},"a":{"a":0,"k":[160.518,342.802,0],"ix":1},"s":{"a":1,"k":[{"i":{"x":[0.6,0.6,0.6],"y":[1,1,1]},"o":{"x":[0.4,0.4,0.4],"y":[0,0,0]},"t":12,"s":[100,100,100]},{"i":{"x":[0.6,0.6,0.6],"y":[1,1,1]},"o":{"x":[0.4,0.4,0.4],"y":[0,0,0]},"t":27,"s":[80,80,100]},{"i":{"x":[0.833,0.833,0.833],"y":[1,1,1]},"o":{"x":[0.167,0.167,0.167],"y":[0,0,0]},"t":42,"s":[100,100,100]},{"i":{"x":[0.6,0.6,0.6],"y":[1,1,1]},"o":{"x":[0.4,0.4,0.4],"y":[0,0,0]},"t":86,"s":[100,100,100]},{"i":{"x":[0.6,0.6,0.6],"y":[1,1,1]},"o":{"x":[0.4,0.4,0.4],"y":[0,0,0]},"t":101,"s":[80,80,100]},{"t":116.000004724777,"s":[100,100,100]}],"ix":6}},"ao":0,"shapes":[{"ty":"gr","it":[{"ty":"gr","it":[{"ind":0,"ty":"sh","ix":1,"ks":{"a":0,"k":{"i":[[0,0],[0,0],[-0.028,-0.329],[-14.63,-1.605],[0,7.247],[-0.352,0],[0,0],[0,0]],"o":[[0,0],[0.331,0],[0.047,0.548],[-4.238,-2.184],[0,-0.352],[0,0],[0,0],[0,0]],"v":[[-10.219,-4.812],[-8.103,-4.812],[-7.467,-4.229],[8.414,9.967],[-2.84,-4.175],[-2.202,-4.812],[-0.085,-4.812],[-5.151,-9.88]],"c":true},"ix":2},"nm":"Path 1","mn":"ADBE Vector Shape - Group","hd":false},{"ind":1,"ty":"sh","ix":2,"ks":{"a":0,"k":{"i":[[0.309,0],[0.484,2.831],[0,0],[0.099,0.238],[-0.183,0.182],[0,0],[-0.17,0],[-0.12,-0.119],[0,0],[0.098,-0.237],[0.258,0],[0,0],[-0.132,-0.048],[0.054,-0.304]],"o":[[-16.869,0],[0,0],[-0.258,0],[-0.099,-0.237],[0,0],[0.12,-0.119],[0.169,0],[0,0],[0.182,0.182],[-0.099,0.238],[0,0],[0.592,8.867],[0.29,0.108],[-0.053,0.304]],"v":[[11.764,11.417],[-8.655,-3.539],[-11.758,-3.539],[-12.346,-3.932],[-12.207,-4.626],[-5.603,-11.232],[-5.151,-11.417],[-4.701,-11.232],[1.905,-4.626],[2.043,-3.932],[1.453,-3.539],[-1.543,-3.539],[11.983,10.182],[12.392,10.892]],"c":true},"ix":2},"nm":"Path 2","mn":"ADBE Vector Shape - Group","hd":false},{"ty":"mm","mm":1,"nm":"Merge Paths 1","mn":"ADBE Vector Filter - Merge","hd":false},{"ty":"fl","c":{"a":0,"k":[0,0.282352954149,0.549019634724,1],"ix":4,"x":"var $bm_rt;\ntry {\n    $bm_rt = thisComp.layer('Controller')('Effects')('Color')('ADBE Color Control-0001');\n} catch (e) {\n    $bm_rt = value;\n}"},"o":{"a":0,"k":100,"ix":5},"r":1,"bm":0,"nm":"Fill 1","mn":"ADBE Vector Graphic - Fill","hd":false},{"ty":"tr","p":{"a":0,"k":[16.566,48.911],"ix":2},"a":{"a":0,"k":[0,0],"ix":1},"s":{"a":0,"k":[100,100],"ix":3},"r":{"a":0,"k":0,"ix":6},"o":{"a":0,"k":100,"ix":7},"sk":{"a":0,"k":0,"ix":4},"sa":{"a":0,"k":0,"ix":5},"nm":"Transform"}],"nm":"Group 8","np":4,"cix":2,"bm":0,"ix":1,"mn":"ADBE Vector Group","hd":false},{"ty":"tr","p":{"a":0,"k":[173.166,331.641],"ix":2},"a":{"a":0,"k":[16.57,48.911],"ix":1},"s":{"a":0,"k":[490,490],"ix":3},"r":{"a":0,"k":0,"ix":6},"o":{"a":0,"k":100,"ix":7},"sk":{"a":0,"k":0,"ix":4},"sa":{"a":0,"k":0,"ix":5},"nm":"Transform"}],"nm":"Layer 13 Outlines - Group 8","np":1,"cix":2,"bm":0,"ix":1,"mn":"ADBE Vector Group","hd":false},{"ty":"gr","it":[{"ty":"gr","it":[{"ind":0,"ty":"sh","ix":1,"ks":{"a":0,"k":{"i":[[0,0],[0,9.835],[0,0],[0,0]],"o":[[0,0],[0,0],[0,0],[-3.268,18.768]],"v":[[10.092,10.781],[-3.874,-4.175],[-0.219,-4.175],[-6.824,-10.781]],"c":true},"ix":2},"nm":"Path 1","mn":"ADBE Vector Shape - Group","hd":false},{"ty":"fl","c":{"a":0,"k":[1,0.835294127464,0.309803932905,1],"ix":4,"x":"var $bm_rt;\ntry {\n    $bm_rt = thisComp.layer('Controller')('Effects')('Color 2')('ADBE Color Control-0001');\n} catch (e) {\n    $bm_rt = value;\n}"},"o":{"a":0,"k":100,"ix":5},"r":1,"bm":0,"nm":"Fill 1","mn":"ADBE Vector Graphic - Fill","hd":false},{"ty":"tr","p":{"a":0,"k":[18.238,48.911],"ix":2},"a":{"a":0,"k":[0,0],"ix":1},"s":{"a":0,"k":[100,100],"ix":3},"r":{"a":0,"k":0,"ix":6},"o":{"a":0,"k":100,"ix":7},"sk":{"a":0,"k":0,"ix":4},"sa":{"a":0,"k":0,"ix":5},"nm":"Transform"}],"nm":"Group 10","np":2,"cix":2,"bm":0,"ix":1,"mn":"ADBE Vector Group","hd":false},{"ty":"tr","p":{"a":0,"k":[188.473,331.639],"ix":2},"a":{"a":0,"k":[19.693,48.911],"ix":1},"s":{"a":0,"k":[490,490],"ix":3},"r":{"a":0,"k":0,"ix":6},"o":{"a":0,"k":100,"ix":7},"sk":{"a":0,"k":0,"ix":4},"sa":{"a":0,"k":0,"ix":5},"nm":"Transform"}],"nm":"Layer 13 Outlines - Group 110","np":1,"cix":2,"bm":0,"ix":2,"mn":"ADBE Vector Group","hd":false},{"ty":"gr","it":[{"ty":"gr","it":[{"ind":0,"ty":"sh","ix":1,"ks":{"a":0,"k":{"i":[[0,0],[-18.635,0],[-3.267,18.767],[0,0]],"o":[[0,0],[0,0],[0,0],[0,0]],"v":[[-8.105,-4.176],[11.761,10.781],[-5.156,-10.781],[-11.761,-4.176]],"c":true},"ix":2},"nm":"Path 1","mn":"ADBE Vector Shape - Group","hd":false},{"ty":"fl","c":{"a":0,"k":[0.937254965305,0.521568655968,0.133333340287,1],"ix":4,"x":"var $bm_rt;\ntry {\n    $bm_rt = thisComp.layer('Controller')('Effects')('Color 4')('ADBE Color Control-0001');\n} catch (e) {\n    $bm_rt = value;\n}"},"o":{"a":0,"k":100,"ix":5},"r":1,"bm":0,"nm":"Fill 1","mn":"ADBE Vector Graphic - Fill","hd":false},{"ty":"tr","p":{"a":0,"k":[16.57,48.911],"ix":2},"a":{"a":0,"k":[0,0],"ix":1},"s":{"a":0,"k":[100,100],"ix":3},"r":{"a":0,"k":0,"ix":6},"o":{"a":0,"k":100,"ix":7},"sk":{"a":0,"k":0,"ix":4},"sa":{"a":0,"k":0,"ix":5},"nm":"Transform"}],"nm":"Group 11","np":2,"cix":2,"bm":0,"ix":1,"mn":"ADBE Vector Group","hd":false},{"ty":"tr","p":{"a":0,"k":[173.167,331.642],"ix":2},"a":{"a":0,"k":[16.57,48.911],"ix":1},"s":{"a":0,"k":[490,490],"ix":3},"r":{"a":0,"k":0,"ix":6},"o":{"a":0,"k":100,"ix":7},"sk":{"a":0,"k":0,"ix":4},"sa":{"a":0,"k":0,"ix":5},"nm":"Transform"}],"nm":"Layer 13 Outlines - Group 111","np":1,"cix":2,"bm":0,"ix":3,"mn":"ADBE Vector Group","hd":false},{"ty":"gr","it":[{"ty":"gr","it":[{"ind":0,"ty":"sh","ix":1,"ks":{"a":0,"k":{"i":[[0,0],[0,0],[0,0],[-18.635,0],[0,9.835],[0,0]],"o":[[0,0],[0,0],[0,0],[0,0],[0,0],[0,0]],"v":[[-5.155,-10.781],[-11.76,-4.176],[-8.105,-4.176],[11.76,10.781],[-2.206,-4.176],[1.449,-4.176]],"c":true},"ix":2},"nm":"Path 1","mn":"ADBE Vector Shape - Group","hd":false},{"ty":"fl","c":{"a":0,"k":[1,0.835294127464,0.309803932905,1],"ix":4,"x":"var $bm_rt;\ntry {\n    $bm_rt = thisComp.layer('Controller')('Effects')('Color 2')('ADBE Color Control-0001');\n} catch (e) {\n    $bm_rt = value;\n}"},"o":{"a":0,"k":100,"ix":5},"r":1,"bm":0,"nm":"Fill 1","mn":"ADBE Vector Graphic - Fill","hd":false},{"ty":"tr","p":{"a":0,"k":[16.57,48.911],"ix":2},"a":{"a":0,"k":[0,0],"ix":1},"s":{"a":0,"k":[100,100],"ix":3},"r":{"a":0,"k":0,"ix":6},"o":{"a":0,"k":100,"ix":7},"sk":{"a":0,"k":0,"ix":4},"sa":{"a":0,"k":0,"ix":5},"nm":"Transform"}],"nm":"Group 13","np":2,"cix":2,"bm":0,"ix":1,"mn":"ADBE Vector Group","hd":false},{"ty":"tr","p":{"a":0,"k":[173.168,331.642],"ix":2},"a":{"a":0,"k":[16.57,48.911],"ix":1},"s":{"a":0,"k":[490,490],"ix":3},"r":{"a":0,"k":0,"ix":6},"o":{"a":0,"k":100,"ix":7},"sk":{"a":0,"k":0,"ix":4},"sa":{"a":0,"k":0,"ix":5},"nm":"Transform"}],"nm":"Layer 13 Outlines - Group 113","np":1,"cix":2,"bm":0,"ix":4,"mn":"ADBE Vector Group","hd":false}],"ip":0,"op":150.000006109625,"st":0,"bm":0},{"ddd":0,"ind":5,"ty":4,"nm":"Shape Layer 4","parent":10,"sr":1,"ks":{"o":{"a":0,"k":100,"ix":11},"r":{"a":0,"k":0,"ix":10},"p":{"a":1,"k":[{"i":{"x":0.6,"y":1},"o":{"x":0.4,"y":0},"t":0,"s":[225.893,299.107,0],"to":[-1.984,1.984,0],"ti":[0,0,0]},{"i":{"x":0.6,"y":1},"o":{"x":0.4,"y":0},"t":27,"s":[213.988,311.012,0],"to":[0,0,0],"ti":[-1.984,1.984,0]},{"i":{"x":0.6,"y":0.6},"o":{"x":0.4,"y":0.4},"t":54,"s":[225.893,299.107,0],"to":[0,0,0],"ti":[0,0,0]},{"i":{"x":0.6,"y":1},"o":{"x":0.4,"y":0},"t":74,"s":[225.893,299.107,0],"to":[-1.984,1.984,0],"ti":[0,0,0]},{"i":{"x":0.6,"y":1},"o":{"x":0.4,"y":0},"t":101,"s":[213.988,311.012,0],"to":[0,0,0],"ti":[-1.984,1.984,0]},{"t":128.000005213547,"s":[225.893,299.107,0]}],"ix":2},"a":{"a":0,"k":[17.857,-25,0],"ix":1},"s":{"a":0,"k":[100,100,100],"ix":6}},"ao":0,"shapes":[{"ty":"gr","it":[{"d":1,"ty":"el","s":{"a":0,"k":[158.929,158.929],"ix":2},"p":{"a":0,"k":[0,0],"ix":3},"nm":"Ellipse Path 1","mn":"ADBE Vector Shape - Ellipse","hd":false},{"ty":"tr","p":{"a":0,"k":[17.857,-25],"ix":2},"a":{"a":0,"k":[0,0],"ix":1},"s":{"a":0,"k":[100,100],"ix":3},"r":{"a":0,"k":0,"ix":6},"o":{"a":0,"k":100,"ix":7},"sk":{"a":0,"k":0,"ix":4},"sa":{"a":0,"k":0,"ix":5},"nm":"Transform"}],"nm":"Ellipse 1","np":3,"cix":2,"bm":0,"ix":1,"mn":"ADBE Vector Group","hd":false}],"ip":0,"op":150.000006109625,"st":0,"bm":0},{"ddd":0,"ind":6,"ty":4,"nm":"Layer 13 Outlines - Group 14 :M","parent":7,"sr":1,"ks":{"o":{"a":0,"k":100,"ix":11},"r":{"a":1,"k":[{"i":{"x":[0.6],"y":[1]},"o":{"x":[0.4],"y":[0]},"t":0,"s":[0]},{"i":{"x":[0.6],"y":[1]},"o":{"x":[0.4],"y":[0]},"t":54,"s":[-180]},{"i":{"x":[0.6],"y":[1]},"o":{"x":[0.4],"y":[0]},"t":74,"s":[-180]},{"t":128.000005213547,"s":[-360]}],"ix":10},"p":{"a":0,"k":[55.729,58.403,0],"ix":2},"a":{"a":0,"k":[293.229,293.225,0],"ix":1},"s":{"a":1,"k":[{"i":{"x":[0.6,0.6,0.6],"y":[1,1,1]},"o":{"x":[0.4,0.4,0.4],"y":[0,0,0]},"t":0,"s":[100,100,100]},{"i":{"x":[0.6,0.6,0.6],"y":[1,1,1]},"o":{"x":[0.4,0.4,0.4],"y":[0,0,0]},"t":27,"s":[85,85,100]},{"i":{"x":[0.6,0.6,0.6],"y":[1,1,1]},"o":{"x":[0.4,0.4,0.4],"y":[0,0,0]},"t":54,"s":[100,100,100]},{"i":{"x":[0.6,0.6,0.6],"y":[1,1,1]},"o":{"x":[0.4,0.4,0.4],"y":[0,0,0]},"t":74,"s":[100,100,100]},{"i":{"x":[0.6,0.6,0.6],"y":[1,1,1]},"o":{"x":[0.4,0.4,0.4],"y":[0,0,0]},"t":101,"s":[85,85,100]},{"t":128.000005213547,"s":[100,100,100]}],"ix":6}},"ao":0,"shapes":[{"ty":"gr","it":[{"ty":"gr","it":[{"ind":0,"ty":"sh","ix":1,"ks":{"a":0,"k":{"i":[[0,-0.596],[0.596,0],[0,0.596],[-0.595,0]],"o":[[0,0.596],[-0.595,0],[0,-0.596],[0.596,0]],"v":[[1.078,0],[0,1.078],[-1.078,0],[0,-1.078]],"c":true},"ix":2},"nm":"Path 1","mn":"ADBE Vector Shape - Group","hd":false},{"ty":"fl","c":{"a":0,"k":[0,0.282352954149,0.549019634724,1],"ix":4,"x":"var $bm_rt;\ntry {\n    $bm_rt = thisComp.layer('Controller')('Effects')('Color')('ADBE Color Control-0001');\n} catch (e) {\n    $bm_rt = value;\n}"},"o":{"a":0,"k":100,"ix":5},"r":1,"bm":0,"nm":"Fill 1","mn":"ADBE Vector Graphic - Fill","hd":false},{"ty":"tr","p":{"a":0,"k":[32.656,41.054],"ix":2},"a":{"a":0,"k":[0,0],"ix":1},"s":{"a":0,"k":[100,100],"ix":3},"r":{"a":0,"k":0,"ix":6},"o":{"a":0,"k":100,"ix":7},"sk":{"a":0,"k":0,"ix":4},"sa":{"a":0,"k":0,"ix":5},"nm":"Transform"}],"nm":"Group 14","np":2,"cix":2,"bm":0,"ix":1,"mn":"ADBE Vector Group","hd":false},{"ty":"tr","p":{"a":0,"k":[251.988,293.142],"ix":2},"a":{"a":0,"k":[32.656,41.054],"ix":1},"s":{"a":0,"k":[490,490],"ix":3},"r":{"a":0,"k":0,"ix":6},"o":{"a":0,"k":100,"ix":7},"sk":{"a":0,"k":0,"ix":4},"sa":{"a":0,"k":0,"ix":5},"nm":"Transform"}],"nm":"Layer 13 Outlines - Group 114","np":1,"cix":2,"bm":0,"ix":1,"mn":"ADBE Vector Group","hd":false},{"ty":"gr","it":[{"ty":"gr","it":[{"ind":0,"ty":"sh","ix":1,"ks":{"a":0,"k":{"i":[[0,-0.596],[0.596,0],[0,0.596],[-0.596,0]],"o":[[0,0.596],[-0.596,0],[0,-0.596],[0.596,0]],"v":[[1.078,0],[0,1.078],[-1.078,0],[0,-1.078]],"c":true},"ix":2},"nm":"Path 1","mn":"ADBE Vector Shape - Group","hd":false},{"ty":"fl","c":{"a":0,"k":[0,0.282352954149,0.549019634724,1],"ix":4,"x":"var $bm_rt;\ntry {\n    $bm_rt = thisComp.layer('Controller')('Effects')('Color')('ADBE Color Control-0001');\n} catch (e) {\n    $bm_rt = value;\n}"},"o":{"a":0,"k":100,"ix":5},"r":1,"bm":0,"nm":"Fill 1","mn":"ADBE Vector Graphic - Fill","hd":false},{"ty":"tr","p":{"a":0,"k":[49.489,41.054],"ix":2},"a":{"a":0,"k":[0,0],"ix":1},"s":{"a":0,"k":[100,100],"ix":3},"r":{"a":0,"k":0,"ix":6},"o":{"a":0,"k":100,"ix":7},"sk":{"a":0,"k":0,"ix":4},"sa":{"a":0,"k":0,"ix":5},"nm":"Transform"}],"nm":"Group 15","np":2,"cix":2,"bm":0,"ix":1,"mn":"ADBE Vector Group","hd":false},{"ty":"tr","p":{"a":0,"k":[334.47,293.142],"ix":2},"a":{"a":0,"k":[49.489,41.054],"ix":1},"s":{"a":0,"k":[490,490],"ix":3},"r":{"a":0,"k":0,"ix":6},"o":{"a":0,"k":100,"ix":7},"sk":{"a":0,"k":0,"ix":4},"sa":{"a":0,"k":0,"ix":5},"nm":"Transform"}],"nm":"Layer 13 Outlines - Group 115","np":1,"cix":2,"bm":0,"ix":2,"mn":"ADBE Vector Group","hd":false},{"ty":"gr","it":[{"ty":"gr","it":[{"ind":0,"ty":"sh","ix":1,"ks":{"a":0,"k":{"i":[[0.353,0],[0,0.352],[0,0],[-0.352,0],[0,-0.352],[0,0]],"o":[[-0.352,0],[0,0],[0,-0.352],[0.353,0],[0,0],[0,0.352]],"v":[[0,1.615],[-0.637,0.978],[-0.637,-0.978],[0,-1.615],[0.637,-0.978],[0.637,0.978]],"c":true},"ix":2},"nm":"Path 1","mn":"ADBE Vector Shape - Group","hd":false},{"ty":"fl","c":{"a":0,"k":[0,0.282352954149,0.549019634724,1],"ix":4,"x":"var $bm_rt;\ntry {\n    $bm_rt = thisComp.layer('Controller')('Effects')('Color')('ADBE Color Control-0001');\n} catch (e) {\n    $bm_rt = value;\n}"},"o":{"a":0,"k":100,"ix":5},"r":1,"bm":0,"nm":"Fill 1","mn":"ADBE Vector Graphic - Fill","hd":false},{"ty":"tr","p":{"a":0,"k":[41.065,49.144],"ix":2},"a":{"a":0,"k":[0,0],"ix":1},"s":{"a":0,"k":[100,100],"ix":3},"r":{"a":0,"k":0,"ix":6},"o":{"a":0,"k":100,"ix":7},"sk":{"a":0,"k":0,"ix":4},"sa":{"a":0,"k":0,"ix":5},"nm":"Transform"}],"nm":"Group 16","np":2,"cix":2,"bm":0,"ix":1,"mn":"ADBE Vector Group","hd":false},{"ty":"tr","p":{"a":0,"k":[293.195,332.783],"ix":2},"a":{"a":0,"k":[41.065,49.144],"ix":1},"s":{"a":0,"k":[490,490],"ix":3},"r":{"a":0,"k":0,"ix":6},"o":{"a":0,"k":100,"ix":7},"sk":{"a":0,"k":0,"ix":4},"sa":{"a":0,"k":0,"ix":5},"nm":"Transform"}],"nm":"Layer 13 Outlines - Group 116","np":1,"cix":2,"bm":0,"ix":3,"mn":"ADBE Vector Group","hd":false},{"ty":"gr","it":[{"ty":"gr","it":[{"ind":0,"ty":"sh","ix":1,"ks":{"a":0,"k":{"i":[[0.353,0],[0,0.352],[0,0],[-0.352,0],[0,-0.351],[0,0]],"o":[[-0.352,0],[0,0],[0,-0.351],[0.353,0],[0,0],[0,0.352]],"v":[[0,1.614],[-0.637,0.977],[-0.637,-0.979],[0,-1.614],[0.637,-0.979],[0.637,0.977]],"c":true},"ix":2},"nm":"Path 1","mn":"ADBE Vector Shape - Group","hd":false},{"ty":"fl","c":{"a":0,"k":[0,0.282352954149,0.549019634724,1],"ix":4,"x":"var $bm_rt;\ntry {\n    $bm_rt = thisComp.layer('Controller')('Effects')('Color')('ADBE Color Control-0001');\n} catch (e) {\n    $bm_rt = value;\n}"},"o":{"a":0,"k":100,"ix":5},"r":1,"bm":0,"nm":"Fill 1","mn":"ADBE Vector Graphic - Fill","hd":false},{"ty":"tr","p":{"a":0,"k":[41.065,32.965],"ix":2},"a":{"a":0,"k":[0,0],"ix":1},"s":{"a":0,"k":[100,100],"ix":3},"r":{"a":0,"k":0,"ix":6},"o":{"a":0,"k":100,"ix":7},"sk":{"a":0,"k":0,"ix":4},"sa":{"a":0,"k":0,"ix":5},"nm":"Transform"}],"nm":"Group 17","np":2,"cix":2,"bm":0,"ix":1,"mn":"ADBE Vector Group","hd":false},{"ty":"tr","p":{"a":0,"k":[293.195,253.505],"ix":2},"a":{"a":0,"k":[41.065,32.965],"ix":1},"s":{"a":0,"k":[490,490],"ix":3},"r":{"a":0,"k":0,"ix":6},"o":{"a":0,"k":100,"ix":7},"sk":{"a":0,"k":0,"ix":4},"sa":{"a":0,"k":0,"ix":5},"nm":"Transform"}],"nm":"Layer 13 Outlines - Group 117","np":1,"cix":2,"bm":0,"ix":4,"mn":"ADBE Vector Group","hd":false},{"ty":"gr","it":[{"ty":"gr","it":[{"ind":0,"ty":"sh","ix":1,"ks":{"a":0,"k":{"i":[[2.51,0],[0.682,1.626],[-0.325,0.135],[-0.137,-0.324],[-1.359,0],[0,1.609],[2.122,0],[0,2.588],[-2.508,0],[-0.684,-1.626],[0.324,-0.136],[0.135,0.324],[1.36,0],[0,-1.608],[-2.113,0],[0,-2.027]],"o":[[-1.895,0],[-0.137,-0.324],[0.323,-0.137],[0.476,1.135],[1.808,0],[0,-1.882],[-2.806,0],[0,-2.31],[1.895,0],[0.137,0.324],[-0.325,0.136],[-0.478,-1.135],[-1.806,0],[0,1.883],[3.366,0],[0,2.311]],"v":[[0.006,7.748],[-4.237,5.072],[-3.897,4.238],[-3.062,4.577],[0.006,6.475],[3.282,3.555],[-0.008,0.636],[-4.558,-3.558],[-0.008,-7.748],[4.236,-5.072],[3.897,-4.239],[3.064,-4.579],[-0.008,-6.476],[-3.283,-3.558],[-0.008,-0.637],[4.558,3.555]],"c":true},"ix":2},"nm":"Path 1","mn":"ADBE Vector Shape - Group","hd":false},{"ty":"fl","c":{"a":0,"k":[0,0.282352954149,0.549019634724,1],"ix":4,"x":"var $bm_rt;\ntry {\n    $bm_rt = thisComp.layer('Controller')('Effects')('Color')('ADBE Color Control-0001');\n} catch (e) {\n    $bm_rt = value;\n}"},"o":{"a":0,"k":100,"ix":5},"r":1,"bm":0,"nm":"Fill 1","mn":"ADBE Vector Graphic - Fill","hd":false},{"ty":"tr","p":{"a":0,"k":[41.072,41.055],"ix":2},"a":{"a":0,"k":[0,0],"ix":1},"s":{"a":0,"k":[100,100],"ix":3},"r":{"a":0,"k":0,"ix":6},"o":{"a":0,"k":100,"ix":7},"sk":{"a":0,"k":0,"ix":4},"sa":{"a":0,"k":0,"ix":5},"nm":"Transform"}],"nm":"Group 18","np":2,"cix":2,"bm":0,"ix":1,"mn":"ADBE Vector Group","hd":false},{"ty":"tr","p":{"a":0,"k":[293.23,293.144],"ix":2},"a":{"a":0,"k":[41.072,41.055],"ix":1},"s":{"a":0,"k":[490,490],"ix":3},"r":{"a":0,"k":0,"ix":6},"o":{"a":0,"k":100,"ix":7},"sk":{"a":0,"k":0,"ix":4},"sa":{"a":0,"k":0,"ix":5},"nm":"Transform"}],"nm":"Layer 13 Outlines - Group 118","np":1,"cix":2,"bm":0,"ix":5,"mn":"ADBE Vector Group","hd":false},{"ty":"gr","it":[{"ty":"gr","it":[{"ind":0,"ty":"sh","ix":1,"ks":{"a":0,"k":{"i":[[4.098,0],[0,8.457],[-8.458,0],[0,-8.458],[1.212,-2.23],[0.311,0.167],[-0.168,0.309],[0,2.342],[7.756,0],[0,-7.756],[-7.755,0],[-2.654,2.656],[-0.249,-0.25],[0.248,-0.249]],"o":[[-8.458,0],[0,-8.458],[8.458,0],[0,2.555],[-0.169,0.309],[-0.31,-0.168],[1.111,-2.043],[0,-7.756],[-7.755,0],[0,7.754],[3.758,0],[0.249,-0.25],[0.248,0.248],[-2.897,2.896]],"v":[[0,15.338],[-15.339,0.001],[0,-15.338],[15.339,0.001],[13.487,7.313],[12.622,7.567],[12.366,6.704],[14.064,0.001],[0,-14.063],[-14.064,0.001],[0,14.064],[9.944,9.946],[10.846,9.946],[10.846,10.847]],"c":true},"ix":2},"nm":"Path 1","mn":"ADBE Vector Shape - Group","hd":false},{"ty":"fl","c":{"a":0,"k":[0,0.282352954149,0.549019634724,1],"ix":4,"x":"var $bm_rt;\ntry {\n    $bm_rt = thisComp.layer('Controller')('Effects')('Color')('ADBE Color Control-0001');\n} catch (e) {\n    $bm_rt = value;\n}"},"o":{"a":0,"k":100,"ix":5},"r":1,"bm":0,"nm":"Fill 1","mn":"ADBE Vector Graphic - Fill","hd":false},{"ty":"tr","p":{"a":0,"k":[41.072,41.071],"ix":2},"a":{"a":0,"k":[0,0],"ix":1},"s":{"a":0,"k":[100,100],"ix":3},"r":{"a":0,"k":0,"ix":6},"o":{"a":0,"k":100,"ix":7},"sk":{"a":0,"k":0,"ix":4},"sa":{"a":0,"k":0,"ix":5},"nm":"Transform"}],"nm":"Group 19","np":2,"cix":2,"bm":0,"ix":1,"mn":"ADBE Vector Group","hd":false},{"ty":"tr","p":{"a":0,"k":[293.229,293.225],"ix":2},"a":{"a":0,"k":[41.072,41.071],"ix":1},"s":{"a":0,"k":[490,490],"ix":3},"r":{"a":0,"k":0,"ix":6},"o":{"a":0,"k":100,"ix":7},"sk":{"a":0,"k":0,"ix":4},"sa":{"a":0,"k":0,"ix":5},"nm":"Transform"}],"nm":"Layer 13 Outlines - Group 119","np":1,"cix":2,"bm":0,"ix":6,"mn":"ADBE Vector Group","hd":false},{"ty":"gr","it":[{"ty":"gr","it":[{"ind":0,"ty":"sh","ix":1,"ks":{"a":0,"k":{"i":[[0,-8.119],[5.342,0],[0,8.119],[-5.685,0]],"o":[[0,8.119],[-5.685,0],[0,-8.119],[5.259,0]],"v":[[11.271,0],[0.491,14.701],[-11.271,0],[0.491,-14.701]],"c":true},"ix":2},"nm":"Path 1","mn":"ADBE Vector Shape - Group","hd":false},{"ty":"fl","c":{"a":0,"k":[1,0.835294127464,0.309803932905,1],"ix":4,"x":"var $bm_rt;\ntry {\n    $bm_rt = thisComp.layer('Controller').effect('Color 6')('ADBE Color Control-0001');\n} catch (e) {\n    $bm_rt = value;\n}"},"o":{"a":0,"k":100,"ix":5},"r":1,"bm":0,"nm":"Fill 1","mn":"ADBE Vector Graphic - Fill","hd":false},{"ty":"tr","p":{"a":0,"k":[40.582,41.072],"ix":2},"a":{"a":0,"k":[0,0],"ix":1},"s":{"a":0,"k":[100,100],"ix":3},"r":{"a":0,"k":0,"ix":6},"o":{"a":0,"k":100,"ix":7},"sk":{"a":0,"k":0,"ix":4},"sa":{"a":0,"k":0,"ix":5},"nm":"Transform"}],"nm":"Group 20","np":2,"cix":2,"bm":0,"ix":1,"mn":"ADBE Vector Group","hd":false},{"ty":"tr","p":{"a":0,"k":[290.827,293.228],"ix":2},"a":{"a":0,"k":[40.582,41.072],"ix":1},"s":{"a":0,"k":[490,490],"ix":3},"r":{"a":0,"k":0,"ix":6},"o":{"a":0,"k":100,"ix":7},"sk":{"a":0,"k":0,"ix":4},"sa":{"a":0,"k":0,"ix":5},"nm":"Transform"}],"nm":"Layer 13 Outlines - Group 220","np":1,"cix":2,"bm":0,"ix":7,"mn":"ADBE Vector Group","hd":false},{"ty":"gr","it":[{"ty":"gr","it":[{"ind":0,"ty":"sh","ix":1,"ks":{"a":0,"k":{"i":[[0,-8.119],[5.342,0],[0,8.119],[-8.12,0]],"o":[[0,8.119],[-8.12,0],[0,-8.119],[5.26,0]],"v":[[12.251,0],[2.45,14.701],[-12.251,0],[2.45,-14.701]],"c":true},"ix":2},"nm":"Path 1","mn":"ADBE Vector Shape - Group","hd":false},{"ty":"fl","c":{"a":0,"k":[1,1,1,1],"ix":4,"x":"var $bm_rt;\ntry {\n    $bm_rt = thisComp.layer('Controller')('Effects')('Color 4')('ADBE Color Control-0001');\n} catch (e) {\n    $bm_rt = value;\n}"},"o":{"a":0,"k":100,"ix":5},"r":1,"bm":0,"nm":"Fill 1","mn":"ADBE Vector Graphic - Fill","hd":false},{"ty":"tr","p":{"a":0,"k":[38.622,41.072],"ix":2},"a":{"a":0,"k":[0,0],"ix":1},"s":{"a":0,"k":[100,100],"ix":3},"r":{"a":0,"k":0,"ix":6},"o":{"a":0,"k":100,"ix":7},"sk":{"a":0,"k":0,"ix":4},"sa":{"a":0,"k":0,"ix":5},"nm":"Transform"}],"nm":"Group 21","np":2,"cix":2,"bm":0,"ix":1,"mn":"ADBE Vector Group","hd":false},{"ty":"tr","p":{"a":0,"k":[281.225,293.228],"ix":2},"a":{"a":0,"k":[38.622,41.072],"ix":1},"s":{"a":0,"k":[490,490],"ix":3},"r":{"a":0,"k":0,"ix":6},"o":{"a":0,"k":100,"ix":7},"sk":{"a":0,"k":0,"ix":4},"sa":{"a":0,"k":0,"ix":5},"nm":"Transform"}],"nm":"Layer 13 Outlines - Group 221","np":1,"cix":2,"bm":0,"ix":8,"mn":"ADBE Vector Group","hd":false},{"ty":"gr","it":[{"ty":"gr","it":[{"ind":0,"ty":"sh","ix":1,"ks":{"a":0,"k":{"i":[[0,-8.119],[8.119,0],[0,8.119],[-8.12,0]],"o":[[0,8.119],[-8.12,0],[0,-8.119],[8.119,0]],"v":[[14.701,0],[0,14.701],[-14.701,0],[0,-14.701]],"c":true},"ix":2},"nm":"Path 1","mn":"ADBE Vector Shape - Group","hd":false},{"ty":"fl","c":{"a":0,"k":[0.937254905701,0.517647087574,0.129411771894,1],"ix":4,"x":"var $bm_rt;\ntry {\n    $bm_rt = thisComp.layer('Controller').effect('Color 7')('ADBE Color Control-0001');\n} catch (e) {\n    $bm_rt = value;\n}"},"o":{"a":0,"k":100,"ix":5},"r":1,"bm":0,"nm":"Fill 1","mn":"ADBE Vector Graphic - Fill","hd":false},{"ty":"tr","p":{"a":0,"k":[41.073,41.072],"ix":2},"a":{"a":0,"k":[0,0],"ix":1},"s":{"a":0,"k":[100,100],"ix":3},"r":{"a":0,"k":0,"ix":6},"o":{"a":0,"k":100,"ix":7},"sk":{"a":0,"k":0,"ix":4},"sa":{"a":0,"k":0,"ix":5},"nm":"Transform"}],"nm":"Group 22","np":2,"cix":2,"bm":0,"ix":1,"mn":"ADBE Vector Group","hd":false},{"ty":"tr","p":{"a":0,"k":[293.232,293.228],"ix":2},"a":{"a":0,"k":[41.073,41.072],"ix":1},"s":{"a":0,"k":[490,490],"ix":3},"r":{"a":0,"k":0,"ix":6},"o":{"a":0,"k":100,"ix":7},"sk":{"a":0,"k":0,"ix":4},"sa":{"a":0,"k":0,"ix":5},"nm":"Transform"}],"nm":"Layer 13 Outlines - Group 222","np":1,"cix":2,"bm":0,"ix":9,"mn":"ADBE Vector Group","hd":false}],"ip":0,"op":150.000006109625,"st":0,"bm":0},{"ddd":0,"ind":7,"ty":4,"nm":"Shape Layer 2","parent":10,"sr":1,"ks":{"o":{"a":0,"k":100,"ix":11},"r":{"a":1,"k":[{"i":{"x":[0.6],"y":[1]},"o":{"x":[0.4],"y":[0]},"t":0,"s":[0]},{"i":{"x":[0.6],"y":[1]},"o":{"x":[0.4],"y":[0]},"t":54,"s":[180]},{"i":{"x":[0.6],"y":[1]},"o":{"x":[0.4],"y":[0]},"t":74,"s":[180]},{"t":128.000005213547,"s":[360]}],"ix":10},"p":{"a":0,"k":[250,250,0],"ix":2},"a":{"a":0,"k":[12.5,15.179,0],"ix":1},"s":{"a":1,"k":[{"i":{"x":[0.6,0.6,0.6],"y":[1,1,1]},"o":{"x":[0.4,0.4,0.4],"y":[0,0,0]},"t":3,"s":[100,100,100]},{"i":{"x":[0.6,0.6,0.6],"y":[1,1,1]},"o":{"x":[0.4,0.4,0.4],"y":[0,0,0]},"t":30,"s":[80,80,100]},{"i":{"x":[0.833,0.833,0.833],"y":[1,1,1]},"o":{"x":[0.167,0.167,0.167],"y":[0,0,0]},"t":57,"s":[100,100,100]},{"i":{"x":[0.6,0.6,0.6],"y":[1,1,1]},"o":{"x":[0.4,0.4,0.4],"y":[0,0,0]},"t":77,"s":[100,100,100]},{"i":{"x":[0.6,0.6,0.6],"y":[1,1,1]},"o":{"x":[0.4,0.4,0.4],"y":[0,0,0]},"t":104,"s":[80,80,100]},{"t":131.000005335739,"s":[100,100,100]}],"ix":6}},"ao":0,"shapes":[{"ty":"gr","it":[{"d":1,"ty":"el","s":{"a":0,"k":[144.643,144.643],"ix":2},"p":{"a":0,"k":[0,0],"ix":3},"nm":"Ellipse Path 1","mn":"ADBE Vector Shape - Ellipse","hd":false},{"ty":"tr","p":{"a":0,"k":[12.5,15.179],"ix":2},"a":{"a":0,"k":[0,0],"ix":1},"s":{"a":0,"k":[100,100],"ix":3},"r":{"a":0,"k":0,"ix":6},"o":{"a":0,"k":100,"ix":7},"sk":{"a":0,"k":0,"ix":4},"sa":{"a":0,"k":0,"ix":5},"nm":"Transform"}],"nm":"Ellipse 1","np":3,"cix":2,"bm":0,"ix":1,"mn":"ADBE Vector Group","hd":false}],"ip":0,"op":150.000006109625,"st":0,"bm":0},{"ddd":0,"ind":8,"ty":4,"nm":"Layer 13 Outlines - Group 23 :M","parent":9,"sr":1,"ks":{"o":{"a":0,"k":100,"ix":11},"r":{"a":1,"k":[{"i":{"x":[0.6],"y":[1]},"o":{"x":[0.4],"y":[0]},"t":0,"s":[0]},{"i":{"x":[0.6],"y":[1]},"o":{"x":[0.4],"y":[0]},"t":54,"s":[-180]},{"i":{"x":[0.6],"y":[1]},"o":{"x":[0.4],"y":[0]},"t":74,"s":[-180]},{"t":128.000005213547,"s":[-360]}],"ix":10},"p":{"a":0,"k":[-30.767,-28.045,0],"ix":2},"a":{"a":0,"k":[206.733,206.776,0],"ix":1},"s":{"a":1,"k":[{"i":{"x":[0.6,0.6,0.6],"y":[1,1,1]},"o":{"x":[0.4,0.4,0.4],"y":[0,0,0]},"t":0,"s":[100,100,100]},{"i":{"x":[0.6,0.6,0.6],"y":[1,1,1]},"o":{"x":[0.4,0.4,0.4],"y":[0,0,0]},"t":27,"s":[85,85,100]},{"i":{"x":[0.6,0.6,0.6],"y":[1,1,1]},"o":{"x":[0.4,0.4,0.4],"y":[0,0,0]},"t":54,"s":[100,100,100]},{"i":{"x":[0.6,0.6,0.6],"y":[1,1,1]},"o":{"x":[0.4,0.4,0.4],"y":[0,0,0]},"t":74,"s":[100,100,100]},{"i":{"x":[0.6,0.6,0.6],"y":[1,1,1]},"o":{"x":[0.4,0.4,0.4],"y":[0,0,0]},"t":101,"s":[85,85,100]},{"t":128.000005213547,"s":[100,100,100]}],"ix":6}},"ao":0,"shapes":[{"ty":"gr","it":[{"ty":"gr","it":[{"ind":0,"ty":"sh","ix":1,"ks":{"a":0,"k":{"i":[[0.353,0],[0,0],[0,0.352],[-0.352,0],[0,0],[0,-0.352]],"o":[[0,0],[-0.352,0],[0,-0.352],[0,0],[0.353,0],[0,0.352]],"v":[[3.251,0.637],[-3.251,0.637],[-3.889,0],[-3.251,-0.637],[3.251,-0.637],[3.889,0]],"c":true},"ix":2},"nm":"Path 1","mn":"ADBE Vector Shape - Group","hd":false},{"ty":"fl","c":{"a":0,"k":[0,0.282352954149,0.549019634724,1],"ix":4,"x":"var $bm_rt;\ntry {\n    $bm_rt = thisComp.layer('Controller')('Effects')('Color')('ADBE Color Control-0001');\n} catch (e) {\n    $bm_rt = value;\n}"},"o":{"a":0,"k":100,"ix":5},"r":1,"bm":0,"nm":"Fill 1","mn":"ADBE Vector Graphic - Fill","hd":false},{"ty":"tr","p":{"a":0,"k":[19.588,25.939],"ix":2},"a":{"a":0,"k":[0,0],"ix":1},"s":{"a":0,"k":[100,100],"ix":3},"r":{"a":0,"k":0,"ix":6},"o":{"a":0,"k":100,"ix":7},"sk":{"a":0,"k":0,"ix":4},"sa":{"a":0,"k":0,"ix":5},"nm":"Transform"}],"nm":"Group 23","np":2,"cix":2,"bm":0,"ix":1,"mn":"ADBE Vector Group","hd":false},{"ty":"tr","p":{"a":0,"k":[187.957,219.076],"ix":2},"a":{"a":0,"k":[19.588,25.939],"ix":1},"s":{"a":0,"k":[490,490],"ix":3},"r":{"a":0,"k":0,"ix":6},"o":{"a":0,"k":100,"ix":7},"sk":{"a":0,"k":0,"ix":4},"sa":{"a":0,"k":0,"ix":5},"nm":"Transform"}],"nm":"Layer 13 Outlines - Group 223","np":1,"cix":2,"bm":0,"ix":1,"mn":"ADBE Vector Group","hd":false},{"ty":"gr","it":[{"ty":"gr","it":[{"ind":0,"ty":"sh","ix":1,"ks":{"a":0,"k":{"i":[[0.353,0],[0,0],[0,0.352],[-0.352,0],[0,0],[0,-0.351]],"o":[[0,0],[-0.352,0],[0,-0.351],[0,0],[0.353,0],[0,0.352]],"v":[[3.251,0.636],[-3.251,0.636],[-3.889,-0.001],[-3.251,-0.636],[3.251,-0.636],[3.889,-0.001]],"c":true},"ix":2},"nm":"Path 1","mn":"ADBE Vector Shape - Group","hd":false},{"ty":"fl","c":{"a":0,"k":[0,0.282352954149,0.549019634724,1],"ix":4,"x":"var $bm_rt;\ntry {\n    $bm_rt = thisComp.layer('Controller')('Effects')('Color')('ADBE Color Control-0001');\n} catch (e) {\n    $bm_rt = value;\n}"},"o":{"a":0,"k":100,"ix":5},"r":1,"bm":0,"nm":"Fill 1","mn":"ADBE Vector Graphic - Fill","hd":false},{"ty":"tr","p":{"a":0,"k":[19.588,20.918],"ix":2},"a":{"a":0,"k":[0,0],"ix":1},"s":{"a":0,"k":[100,100],"ix":3},"r":{"a":0,"k":0,"ix":6},"o":{"a":0,"k":100,"ix":7},"sk":{"a":0,"k":0,"ix":4},"sa":{"a":0,"k":0,"ix":5},"nm":"Transform"}],"nm":"Group 24","np":2,"cix":2,"bm":0,"ix":1,"mn":"ADBE Vector Group","hd":false},{"ty":"tr","p":{"a":0,"k":[187.957,194.473],"ix":2},"a":{"a":0,"k":[19.588,20.918],"ix":1},"s":{"a":0,"k":[490,490],"ix":3},"r":{"a":0,"k":0,"ix":6},"o":{"a":0,"k":100,"ix":7},"sk":{"a":0,"k":0,"ix":4},"sa":{"a":0,"k":0,"ix":5},"nm":"Transform"}],"nm":"Layer 13 Outlines - Group 224","np":1,"cix":2,"bm":0,"ix":2,"mn":"ADBE Vector Group","hd":false},{"ty":"gr","it":[{"ty":"gr","it":[{"ind":0,"ty":"sh","ix":1,"ks":{"a":0,"k":{"i":[[1.361,0],[0,4.504],[-3.402,0],[-1.035,-0.951],[0.239,-0.26],[0.258,0.238],[0.946,0],[0,-3.802],[-2.7,0],[-0.831,0.832],[-0.248,-0.249],[0.249,-0.249]],"o":[[-3.402,0],[0,-4.503],[1.272,0],[0.259,0.238],[-0.237,0.257],[-0.797,-0.731],[-2.7,0],[0,3.802],[1.016,0],[0.249,-0.249],[0.249,0.248],[-1.077,1.077]],"v":[[1.099,8.168],[-5.074,0],[1.099,-8.168],[4.624,-6.714],[4.663,-5.813],[3.764,-5.776],[1.099,-6.894],[-3.798,0],[1.099,6.894],[3.923,5.622],[4.825,5.622],[4.825,6.522]],"c":true},"ix":2},"nm":"Path 1","mn":"ADBE Vector Shape - Group","hd":false},{"ty":"fl","c":{"a":0,"k":[0,0.282352954149,0.549019634724,1],"ix":4,"x":"var $bm_rt;\ntry {\n    $bm_rt = thisComp.layer('Controller')('Effects')('Color')('ADBE Color Control-0001');\n} catch (e) {\n    $bm_rt = value;\n}"},"o":{"a":0,"k":100,"ix":5},"r":1,"bm":0,"nm":"Fill 1","mn":"ADBE Vector Graphic - Fill","hd":false},{"ty":"tr","p":{"a":0,"k":[22.745,23.428],"ix":2},"a":{"a":0,"k":[0,0],"ix":1},"s":{"a":0,"k":[100,100],"ix":3},"r":{"a":0,"k":0,"ix":6},"o":{"a":0,"k":100,"ix":7},"sk":{"a":0,"k":0,"ix":4},"sa":{"a":0,"k":0,"ix":5},"nm":"Transform"}],"nm":"Group 25","np":2,"cix":2,"bm":0,"ix":1,"mn":"ADBE Vector Group","hd":false},{"ty":"tr","p":{"a":0,"k":[203.271,206.774],"ix":2},"a":{"a":0,"k":[22.713,23.428],"ix":1},"s":{"a":0,"k":[490,490],"ix":3},"r":{"a":0,"k":0,"ix":6},"o":{"a":0,"k":100,"ix":7},"sk":{"a":0,"k":0,"ix":4},"sa":{"a":0,"k":0,"ix":5},"nm":"Transform"}],"nm":"Layer 13 Outlines - Group 225","np":1,"cix":2,"bm":0,"ix":3,"mn":"ADBE Vector Group","hd":false},{"ty":"gr","it":[{"ty":"gr","it":[{"ind":0,"ty":"sh","ix":1,"ks":{"a":0,"k":{"i":[[7.187,0],[0,8.458],[-8.458,0],[-0.398,-8.175],[0.352,-0.017],[0.017,0.351],[7.512,0],[0,-7.755],[-7.756,0],[-1.477,6.412],[-0.345,-0.08],[0.078,-0.344]],"o":[[-8.458,0],[0,-8.458],[8.192,0],[0.017,0.352],[-0.348,0.006],[-0.364,-7.496],[-7.756,0],[0,7.755],[6.59,0],[0.08,-0.344],[0.343,0.078],[-1.613,6.992]],"v":[[0.001,15.338],[-15.338,-0.001],[0.001,-15.338],[15.321,-0.76],[14.715,-0.092],[14.048,-0.696],[0.001,-14.063],[-14.063,-0.001],[0.001,14.064],[13.704,3.175],[14.469,2.697],[14.947,3.462]],"c":true},"ix":2},"nm":"Path 1","mn":"ADBE Vector Shape - Group","hd":false},{"ty":"fl","c":{"a":0,"k":[0,0.282352954149,0.549019634724,1],"ix":4,"x":"var $bm_rt;\ntry {\n    $bm_rt = thisComp.layer('Controller')('Effects')('Color')('ADBE Color Control-0001');\n} catch (e) {\n    $bm_rt = value;\n}"},"o":{"a":0,"k":100,"ix":5},"r":1,"bm":0,"nm":"Fill 1","mn":"ADBE Vector Graphic - Fill","hd":false},{"ty":"tr","p":{"a":0,"k":[23.428,23.429],"ix":2},"a":{"a":0,"k":[0,0],"ix":1},"s":{"a":0,"k":[100,100],"ix":3},"r":{"a":0,"k":0,"ix":6},"o":{"a":0,"k":100,"ix":7},"sk":{"a":0,"k":0,"ix":4},"sa":{"a":0,"k":0,"ix":5},"nm":"Transform"}],"nm":"Group 26","np":2,"cix":2,"bm":0,"ix":1,"mn":"ADBE Vector Group","hd":false},{"ty":"tr","p":{"a":0,"k":[206.733,206.776],"ix":2},"a":{"a":0,"k":[23.42,23.429],"ix":1},"s":{"a":0,"k":[490,490],"ix":3},"r":{"a":0,"k":0,"ix":6},"o":{"a":0,"k":100,"ix":7},"sk":{"a":0,"k":0,"ix":4},"sa":{"a":0,"k":0,"ix":5},"nm":"Transform"}],"nm":"Layer 13 Outlines - Group 226","np":1,"cix":2,"bm":0,"ix":4,"mn":"ADBE Vector Group","hd":false},{"ty":"gr","it":[{"ty":"gr","it":[{"ind":0,"ty":"sh","ix":1,"ks":{"a":0,"k":{"i":[[0,-8.119],[3.893,0],[0,8.119],[-5.601,0]],"o":[[0,8.119],[-5.846,0],[0,-8.119],[5.391,0]],"v":[[11.271,0],[0.49,14.701],[-11.271,0],[0.49,-14.701]],"c":true},"ix":2},"nm":"Path 1","mn":"ADBE Vector Shape - Group","hd":false},{"ty":"fl","c":{"a":0,"k":[1,0.835294127464,0.309803932905,1],"ix":4,"x":"var $bm_rt;\ntry {\n    $bm_rt = thisComp.layer('Controller').effect('Color 8')('ADBE Color Control-0001');\n} catch (e) {\n    $bm_rt = value;\n}"},"o":{"a":0,"k":100,"ix":5},"r":1,"bm":0,"nm":"Fill 1","mn":"ADBE Vector Graphic - Fill","hd":false},{"ty":"tr","p":{"a":0,"k":[22.939,23.428],"ix":2},"a":{"a":0,"k":[0,0],"ix":1},"s":{"a":0,"k":[100,100],"ix":3},"r":{"a":0,"k":0,"ix":6},"o":{"a":0,"k":100,"ix":7},"sk":{"a":0,"k":0,"ix":4},"sa":{"a":0,"k":0,"ix":5},"nm":"Transform"}],"nm":"Group 27","np":2,"cix":2,"bm":0,"ix":1,"mn":"ADBE Vector Group","hd":false},{"ty":"tr","p":{"a":0,"k":[204.378,206.775],"ix":2},"a":{"a":0,"k":[22.939,23.428],"ix":1},"s":{"a":0,"k":[490,490],"ix":3},"r":{"a":0,"k":0,"ix":6},"o":{"a":0,"k":100,"ix":7},"sk":{"a":0,"k":0,"ix":4},"sa":{"a":0,"k":0,"ix":5},"nm":"Transform"}],"nm":"Layer 13 Outlines - Group 227","np":1,"cix":2,"bm":0,"ix":5,"mn":"ADBE Vector Group","hd":false},{"ty":"gr","it":[{"ty":"gr","it":[{"ind":0,"ty":"sh","ix":1,"ks":{"a":0,"k":{"i":[[0,-8.119],[3.894,0],[0,8.119],[-8.119,0]],"o":[[0,8.119],[-8.119,0],[0,-8.119],[5.392,0]],"v":[[12.251,0],[2.45,14.701],[-12.251,0],[2.45,-14.701]],"c":true},"ix":2},"nm":"Path 1","mn":"ADBE Vector Shape - Group","hd":false},{"ty":"fl","c":{"a":0,"k":[1,1,1,1],"ix":4,"x":"var $bm_rt;\ntry {\n    $bm_rt = thisComp.layer('Controller')('Effects')('Color 4')('ADBE Color Control-0001');\n} catch (e) {\n    $bm_rt = value;\n}"},"o":{"a":0,"k":100,"ix":5},"r":1,"bm":0,"nm":"Fill 1","mn":"ADBE Vector Graphic - Fill","hd":false},{"ty":"tr","p":{"a":0,"k":[20.979,23.428],"ix":2},"a":{"a":0,"k":[0,0],"ix":1},"s":{"a":0,"k":[100,100],"ix":3},"r":{"a":0,"k":0,"ix":6},"o":{"a":0,"k":100,"ix":7},"sk":{"a":0,"k":0,"ix":4},"sa":{"a":0,"k":0,"ix":5},"nm":"Transform"}],"nm":"Group 28","np":2,"cix":2,"bm":0,"ix":1,"mn":"ADBE Vector Group","hd":false},{"ty":"tr","p":{"a":0,"k":[194.771,206.775],"ix":2},"a":{"a":0,"k":[20.979,23.428],"ix":1},"s":{"a":0,"k":[490,490],"ix":3},"r":{"a":0,"k":0,"ix":6},"o":{"a":0,"k":100,"ix":7},"sk":{"a":0,"k":0,"ix":4},"sa":{"a":0,"k":0,"ix":5},"nm":"Transform"}],"nm":"Layer 13 Outlines - Group 228","np":1,"cix":2,"bm":0,"ix":6,"mn":"ADBE Vector Group","hd":false},{"ty":"gr","it":[{"ty":"gr","it":[{"ind":0,"ty":"sh","ix":1,"ks":{"a":0,"k":{"i":[[0,-8.119],[8.119,0],[0,8.119],[-8.119,0]],"o":[[0,8.119],[-8.119,0],[0,-8.119],[8.119,0]],"v":[[14.701,0],[0,14.701],[-14.701,0],[0,-14.701]],"c":true},"ix":2},"nm":"Path 1","mn":"ADBE Vector Shape - Group","hd":false},{"ty":"fl","c":{"a":0,"k":[0.937254905701,0.517647087574,0.129411771894,1],"ix":4,"x":"var $bm_rt;\ntry {\n    $bm_rt = thisComp.layer('Controller').effect('Color 9')('ADBE Color Control-0001');\n} catch (e) {\n    $bm_rt = value;\n}"},"o":{"a":0,"k":100,"ix":5},"r":1,"bm":0,"nm":"Fill 1","mn":"ADBE Vector Graphic - Fill","hd":false},{"ty":"tr","p":{"a":0,"k":[23.429,23.428],"ix":2},"a":{"a":0,"k":[0,0],"ix":1},"s":{"a":0,"k":[100,100],"ix":3},"r":{"a":0,"k":0,"ix":6},"o":{"a":0,"k":100,"ix":7},"sk":{"a":0,"k":0,"ix":4},"sa":{"a":0,"k":0,"ix":5},"nm":"Transform"}],"nm":"Group 29","np":2,"cix":2,"bm":0,"ix":1,"mn":"ADBE Vector Group","hd":false},{"ty":"tr","p":{"a":0,"k":[206.778,206.775],"ix":2},"a":{"a":0,"k":[23.429,23.428],"ix":1},"s":{"a":0,"k":[490,490],"ix":3},"r":{"a":0,"k":0,"ix":6},"o":{"a":0,"k":100,"ix":7},"sk":{"a":0,"k":0,"ix":4},"sa":{"a":0,"k":0,"ix":5},"nm":"Transform"}],"nm":"Layer 13 Outlines - Group 229","np":1,"cix":2,"bm":0,"ix":7,"mn":"ADBE Vector Group","hd":false}],"ip":0,"op":150.000006109625,"st":0,"bm":0},{"ddd":0,"ind":9,"ty":4,"nm":"Shape Layer 1","parent":10,"sr":1,"ks":{"o":{"a":0,"k":100,"ix":11},"r":{"a":1,"k":[{"i":{"x":[0.6],"y":[1]},"o":{"x":[0.4],"y":[0]},"t":0,"s":[0]},{"i":{"x":[0.6],"y":[1]},"o":{"x":[0.4],"y":[0]},"t":54,"s":[180]},{"i":{"x":[0.6],"y":[1]},"o":{"x":[0.4],"y":[0]},"t":74,"s":[180]},{"t":128.000005213547,"s":[360]}],"ix":10},"p":{"a":0,"k":[250,250,0],"ix":2},"a":{"a":0,"k":[12.5,15.179,0],"ix":1},"s":{"a":1,"k":[{"i":{"x":[0.6,0.6,0.6],"y":[1,1,1]},"o":{"x":[0.4,0.4,0.4],"y":[0,0,0]},"t":3,"s":[100,100,100]},{"i":{"x":[0.6,0.6,0.6],"y":[1,1,1]},"o":{"x":[0.4,0.4,0.4],"y":[0,0,0]},"t":30,"s":[80,80,100]},{"i":{"x":[0.833,0.833,0.833],"y":[1,1,1]},"o":{"x":[0.167,0.167,0.167],"y":[0,0,0]},"t":57,"s":[100,100,100]},{"i":{"x":[0.6,0.6,0.6],"y":[1,1,1]},"o":{"x":[0.4,0.4,0.4],"y":[0,0,0]},"t":77,"s":[100,100,100]},{"i":{"x":[0.6,0.6,0.6],"y":[1,1,1]},"o":{"x":[0.4,0.4,0.4],"y":[0,0,0]},"t":104,"s":[80,80,100]},{"t":131.000005335739,"s":[100,100,100]}],"ix":6}},"ao":0,"shapes":[{"ty":"gr","it":[{"d":1,"ty":"el","s":{"a":0,"k":[144.643,144.643],"ix":2},"p":{"a":0,"k":[0,0],"ix":3},"nm":"Ellipse Path 1","mn":"ADBE Vector Shape - Ellipse","hd":false},{"ty":"tr","p":{"a":0,"k":[12.5,15.179],"ix":2},"a":{"a":0,"k":[0,0],"ix":1},"s":{"a":0,"k":[100,100],"ix":3},"r":{"a":0,"k":0,"ix":6},"o":{"a":0,"k":100,"ix":7},"sk":{"a":0,"k":0,"ix":4},"sa":{"a":0,"k":0,"ix":5},"nm":"Transform"}],"nm":"Ellipse 1","np":3,"cix":2,"bm":0,"ix":1,"mn":"ADBE Vector Group","hd":false}],"ip":0,"op":150.000006109625,"st":0,"bm":0},{"ddd":0,"ind":10,"ty":4,"nm":"Layer 13 Outlines - Group 30 :M","sr":1,"ks":{"o":{"a":0,"k":100,"ix":11},"r":{"a":1,"k":[{"i":{"x":[0.6],"y":[1]},"o":{"x":[0.4],"y":[0]},"t":54,"s":[0]},{"i":{"x":[0.6],"y":[1]},"o":{"x":[0.4],"y":[0]},"t":59,"s":[5]},{"i":{"x":[0.6],"y":[1]},"o":{"x":[0.4],"y":[0]},"t":64,"s":[-5]},{"i":{"x":[0.6],"y":[1]},"o":{"x":[0.4],"y":[0]},"t":69,"s":[5]},{"i":{"x":[0.833],"y":[1]},"o":{"x":[0.167],"y":[0]},"t":74,"s":[0]},{"i":{"x":[0.6],"y":[1]},"o":{"x":[0.4],"y":[0]},"t":128,"s":[0]},{"i":{"x":[0.6],"y":[1]},"o":{"x":[0.4],"y":[0]},"t":133,"s":[5]},{"i":{"x":[0.6],"y":[1]},"o":{"x":[0.4],"y":[0]},"t":138,"s":[-5]},{"i":{"x":[0.6],"y":[1]},"o":{"x":[0.4],"y":[0]},"t":143,"s":[5]},{"t":148.000006028164,"s":[0]}],"ix":10},"p":{"a":0,"k":[250,250,0],"ix":2},"a":{"a":0,"k":[250,250,0],"ix":1},"s":{"a":1,"k":[{"i":{"x":[0.6,0.6,0.6],"y":[1,1,1]},"o":{"x":[0.4,0.4,0.4],"y":[0,0,0]},"t":0,"s":[100,100,100]},{"i":{"x":[0.6,0.6,0.6],"y":[1,1,1]},"o":{"x":[0.4,0.4,0.4],"y":[0,0,0]},"t":27,"s":[120,120,100]},{"i":{"x":[0.6,0.6,0.6],"y":[1,1,1]},"o":{"x":[0.4,0.4,0.4],"y":[0,0,0]},"t":54,"s":[100,100,100]},{"i":{"x":[0.6,0.6,0.6],"y":[1,1,1]},"o":{"x":[0.4,0.4,0.4],"y":[0,0,0]},"t":74,"s":[100,100,100]},{"i":{"x":[0.6,0.6,0.6],"y":[1,1,1]},"o":{"x":[0.4,0.4,0.4],"y":[0,0,0]},"t":101,"s":[120,120,100]},{"i":{"x":[0.6,0.6,0.6],"y":[1,1,1]},"o":{"x":[0.167,0.167,0.167],"y":[0,0,0]},"t":128,"s":[100,100,100]},{"t":148.000006028164,"s":[100,100,100]}],"ix":6}},"ao":0,"shapes":[{"ty":"gr","it":[{"ty":"gr","it":[{"ind":0,"ty":"sh","ix":1,"ks":{"a":0,"k":{"i":[[7.917,0],[0,0],[0,0.352],[-0.352,0],[0,0],[0,7.213],[0,0],[7.215,0],[0,0],[0,0.351],[-0.353,0],[0,0],[0,-7.918],[0,0]],"o":[[0,0],[-0.352,0],[0,-0.351],[0,0],[7.215,0],[0,0],[0,-7.214],[0,0],[-0.353,0],[0,-0.353],[0,0],[7.917,0],[0,0],[0,7.916]],"v":[[6.722,31.999],[-5.711,31.999],[-6.348,31.363],[-5.711,30.727],[6.722,30.727],[19.806,17.643],[19.806,-17.641],[6.722,-30.725],[-20.441,-30.725],[-21.079,-31.361],[-20.441,-31.999],[6.722,-31.999],[21.079,-17.641],[21.079,17.643]],"c":true},"ix":2},"nm":"Path 1","mn":"ADBE Vector Shape - Group","hd":false},{"ty":"fl","c":{"a":0,"k":[0,0.282352954149,0.549019634724,1],"ix":4,"x":"var $bm_rt;\ntry {\n    $bm_rt = thisComp.layer('Controller')('Effects')('Color')('ADBE Color Control-0001');\n} catch (e) {\n    $bm_rt = value;\n}"},"o":{"a":0,"k":100,"ix":5},"r":1,"bm":0,"nm":"Fill 1","mn":"ADBE Vector Graphic - Fill","hd":false},{"ty":"tr","p":{"a":0,"k":[43.17,32.25],"ix":2},"a":{"a":0,"k":[0,0],"ix":1},"s":{"a":0,"k":[100,100],"ix":3},"r":{"a":0,"k":0,"ix":6},"o":{"a":0,"k":100,"ix":7},"sk":{"a":0,"k":0,"ix":4},"sa":{"a":0,"k":0,"ix":5},"nm":"Transform"}],"nm":"Group 30","np":2,"cix":2,"bm":0,"ix":1,"mn":"ADBE Vector Group","hd":false},{"ty":"tr","p":{"a":0,"k":[303.51,250.001],"ix":2},"a":{"a":0,"k":[43.17,32.25],"ix":1},"s":{"a":0,"k":[490,490],"ix":3},"r":{"a":0,"k":0,"ix":6},"o":{"a":0,"k":100,"ix":7},"sk":{"a":0,"k":0,"ix":4},"sa":{"a":0,"k":0,"ix":5},"nm":"Transform"}],"nm":"Layer 13 Outlines - Group 330","np":1,"cix":2,"bm":0,"ix":1,"mn":"ADBE Vector Group","hd":false},{"ty":"gr","it":[{"ty":"gr","it":[{"ind":0,"ty":"sh","ix":1,"ks":{"a":0,"k":{"i":[[0.353,0],[0,0],[0,7.916],[0,0],[-0.353,0],[0,-0.352],[0,0],[-7.215,0],[0,0],[0,-0.351]],"o":[[0,0],[-7.917,0],[0,0],[0,-0.352],[0.351,0],[0,0],[0,7.213],[0,0],[0.353,0],[0,0.352]],"v":[[16.325,12.626],[-2.605,12.626],[-16.963,-1.731],[-16.963,-11.989],[-16.325,-12.626],[-15.689,-11.989],[-15.689,-1.731],[-2.605,11.353],[16.325,11.353],[16.963,11.989]],"c":true},"ix":2},"nm":"Path 1","mn":"ADBE Vector Shape - Group","hd":false},{"ty":"fl","c":{"a":0,"k":[0,0.282352954149,0.549019634724,1],"ix":4,"x":"var $bm_rt;\ntry {\n    $bm_rt = thisComp.layer('Controller')('Effects')('Color')('ADBE Color Control-0001');\n} catch (e) {\n    $bm_rt = value;\n}"},"o":{"a":0,"k":100,"ix":5},"r":1,"bm":0,"nm":"Fill 1","mn":"ADBE Vector Graphic - Fill","hd":false},{"ty":"tr","p":{"a":0,"k":[17.213,51.623],"ix":2},"a":{"a":0,"k":[0,0],"ix":1},"s":{"a":0,"k":[100,100],"ix":3},"r":{"a":0,"k":0,"ix":6},"o":{"a":0,"k":100,"ix":7},"sk":{"a":0,"k":0,"ix":4},"sa":{"a":0,"k":0,"ix":5},"nm":"Transform"}],"nm":"Group 31","np":2,"cix":2,"bm":0,"ix":1,"mn":"ADBE Vector Group","hd":false},{"ty":"tr","p":{"a":0,"k":[176.321,344.931],"ix":2},"a":{"a":0,"k":[17.213,51.623],"ix":1},"s":{"a":0,"k":[490,490],"ix":3},"r":{"a":0,"k":0,"ix":6},"o":{"a":0,"k":100,"ix":7},"sk":{"a":0,"k":0,"ix":4},"sa":{"a":0,"k":0,"ix":5},"nm":"Transform"}],"nm":"Layer 13 Outlines - Group 331","np":1,"cix":2,"bm":0,"ix":2,"mn":"ADBE Vector Group","hd":false},{"ty":"gr","it":[{"ty":"gr","it":[{"ind":0,"ty":"sh","ix":1,"ks":{"a":0,"k":{"i":[[0.352,0],[0,0.352],[0,0],[-7.917,0],[0,0],[0,-0.352],[0.351,0],[0,0],[0,-7.215],[0,0]],"o":[[-0.353,0],[0,0],[0,-7.918],[0,0],[0.351,0],[0,0.352],[0,0],[-7.215,0],[0,0],[0,0.352]],"v":[[-8.96,18.05],[-9.598,17.413],[-9.598,-3.691],[4.761,-18.05],[8.961,-18.05],[9.598,-17.412],[8.961,-16.775],[4.761,-16.775],[-8.323,-3.691],[-8.323,17.413]],"c":true},"ix":2},"nm":"Path 1","mn":"ADBE Vector Shape - Group","hd":false},{"ty":"fl","c":{"a":0,"k":[0,0.282352954149,0.549019634724,1],"ix":4,"x":"var $bm_rt;\ntry {\n    $bm_rt = thisComp.layer('Controller')('Effects')('Color')('ADBE Color Control-0001');\n} catch (e) {\n    $bm_rt = value;\n}"},"o":{"a":0,"k":100,"ix":5},"r":1,"bm":0,"nm":"Fill 1","mn":"ADBE Vector Graphic - Fill","hd":false},{"ty":"tr","p":{"a":0,"k":[9.848,18.301],"ix":2},"a":{"a":0,"k":[0,0],"ix":1},"s":{"a":0,"k":[100,100],"ix":3},"r":{"a":0,"k":0,"ix":6},"o":{"a":0,"k":100,"ix":7},"sk":{"a":0,"k":0,"ix":4},"sa":{"a":0,"k":0,"ix":5},"nm":"Transform"}],"nm":"Group 32","np":2,"cix":2,"bm":0,"ix":1,"mn":"ADBE Vector Group","hd":false},{"ty":"tr","p":{"a":0,"k":[140.23,181.649],"ix":2},"a":{"a":0,"k":[9.848,18.301],"ix":1},"s":{"a":0,"k":[490,490],"ix":3},"r":{"a":0,"k":0,"ix":6},"o":{"a":0,"k":100,"ix":7},"sk":{"a":0,"k":0,"ix":4},"sa":{"a":0,"k":0,"ix":5},"nm":"Transform"}],"nm":"Layer 13 Outlines - Group 332","np":1,"cix":2,"bm":0,"ix":3,"mn":"ADBE Vector Group","hd":false},{"ty":"gr","it":[{"ty":"gr","it":[{"ind":0,"ty":"sh","ix":1,"ks":{"a":0,"k":{"i":[[7.732,0],[0,0],[0,7.732],[0,0],[-7.731,0],[0,0],[0,-7.732],[0,0]],"o":[[0,0],[-7.731,0],[0,0],[0,-7.732],[0,0],[7.732,0],[0,0],[0,7.732]],"v":[[13.443,31.362],[-13.443,31.362],[-27.443,17.362],[-27.443,-17.362],[-13.443,-31.362],[13.443,-31.362],[27.443,-17.362],[27.443,17.362]],"c":true},"ix":2},"nm":"Path 1","mn":"ADBE Vector Shape - Group","hd":false},{"ty":"fl","c":{"a":0,"k":[0.572549045086,0.819607853889,0.945098042488,1],"ix":4,"x":"var $bm_rt;\ntry {\n    $bm_rt = thisComp.layer('Controller').effect('Color 10')('ADBE Color Control-0001');\n} catch (e) {\n    $bm_rt = value;\n}"},"o":{"a":0,"k":100,"ix":5},"r":1,"bm":0,"nm":"Fill 1","mn":"ADBE Vector Graphic - Fill","hd":false},{"ty":"tr","p":{"a":0,"k":[31.577,31.987],"ix":2},"a":{"a":0,"k":[0,0],"ix":1},"s":{"a":0,"k":[100,100],"ix":3},"r":{"a":0,"k":0,"ix":6},"o":{"a":0,"k":100,"ix":7},"sk":{"a":0,"k":0,"ix":4},"sa":{"a":0,"k":0,"ix":5},"nm":"Transform"}],"nm":"Group 33","np":2,"cix":2,"bm":0,"ix":1,"mn":"ADBE Vector Group","hd":false},{"ty":"tr","p":{"a":0,"k":[246.705,248.711],"ix":2},"a":{"a":0,"k":[31.577,31.987],"ix":1},"s":{"a":0,"k":[490,490],"ix":3},"r":{"a":0,"k":0,"ix":6},"o":{"a":0,"k":100,"ix":7},"sk":{"a":0,"k":0,"ix":4},"sa":{"a":0,"k":0,"ix":5},"nm":"Transform"}],"nm":"Layer 13 Outlines - Group 333","np":1,"cix":2,"bm":0,"ix":4,"mn":"ADBE Vector Group","hd":false},{"ty":"gr","it":[{"ty":"gr","it":[{"ind":0,"ty":"sh","ix":1,"ks":{"a":0,"k":{"i":[[7.732,0],[0,0],[0,7.731],[0,0],[-7.733,0],[0,0],[0,-7.731],[0,0]],"o":[[0,0],[-7.733,0],[0,0],[0,-7.731],[0,0],[7.732,0],[0,0],[0,7.731]],"v":[[13.932,31.363],[-13.932,31.363],[-27.932,17.363],[-27.932,-17.363],[-13.932,-31.363],[13.932,-31.363],[27.932,-17.363],[27.932,17.363]],"c":true},"ix":2},"nm":"Path 1","mn":"ADBE Vector Shape - Group","hd":false},{"ty":"fl","c":{"a":0,"k":[1,1,1,1],"ix":4,"x":"var $bm_rt;\ntry {\n    $bm_rt = thisComp.layer('Controller')('Effects')('Color 4')('ADBE Color Control-0001');\n} catch (e) {\n    $bm_rt = value;\n}"},"o":{"a":0,"k":100,"ix":5},"r":1,"bm":0,"nm":"Fill 1","mn":"ADBE Vector Graphic - Fill","hd":false},{"ty":"tr","p":{"a":0,"k":[28.82,32.25],"ix":2},"a":{"a":0,"k":[0,0],"ix":1},"s":{"a":0,"k":[100,100],"ix":3},"r":{"a":0,"k":0,"ix":6},"o":{"a":0,"k":100,"ix":7},"sk":{"a":0,"k":0,"ix":4},"sa":{"a":0,"k":0,"ix":5},"nm":"Transform"}],"nm":"Group 34","np":2,"cix":2,"bm":0,"ix":1,"mn":"ADBE Vector Group","hd":false},{"ty":"tr","p":{"a":0,"k":[233.195,250],"ix":2},"a":{"a":0,"k":[28.82,32.25],"ix":1},"s":{"a":0,"k":[490,490],"ix":3},"r":{"a":0,"k":0,"ix":6},"o":{"a":0,"k":100,"ix":7},"sk":{"a":0,"k":0,"ix":4},"sa":{"a":0,"k":0,"ix":5},"nm":"Transform"}],"nm":"Layer 13 Outlines - Group 334","np":1,"cix":2,"bm":0,"ix":5,"mn":"ADBE Vector Group","hd":false},{"ty":"gr","it":[{"ty":"gr","it":[{"ind":0,"ty":"sh","ix":1,"ks":{"a":0,"k":{"i":[[7.731,0],[0,0],[0,7.731],[0,0],[-7.731,0],[0,0],[0,-7.731],[0,0]],"o":[[0,0],[-7.731,0],[0,0],[0,-7.731],[0,0],[7.731,0],[0,0],[0,7.731]],"v":[[16.383,31.363],[-16.383,31.363],[-30.383,17.363],[-30.383,-17.363],[-16.383,-31.363],[16.383,-31.363],[30.383,-17.363],[30.383,17.363]],"c":true},"ix":2},"nm":"Path 1","mn":"ADBE Vector Shape - Group","hd":false},{"ty":"fl","c":{"a":0,"k":[0.133333340287,0.61960786581,0.796078443527,1],"ix":4,"x":"var $bm_rt;\ntry {\n    $bm_rt = thisComp.layer('Controller').effect('Color 11')('ADBE Color Control-0001');\n} catch (e) {\n    $bm_rt = value;\n}"},"o":{"a":0,"k":100,"ix":5},"r":1,"bm":0,"nm":"Fill 1","mn":"ADBE Vector Graphic - Fill","hd":false},{"ty":"tr","p":{"a":0,"k":[33.231,32.25],"ix":2},"a":{"a":0,"k":[0,0],"ix":1},"s":{"a":0,"k":[100,100],"ix":3},"r":{"a":0,"k":0,"ix":6},"o":{"a":0,"k":100,"ix":7},"sk":{"a":0,"k":0,"ix":4},"sa":{"a":0,"k":0,"ix":5},"nm":"Transform"}],"nm":"Group 35","np":2,"cix":2,"bm":0,"ix":1,"mn":"ADBE Vector Group","hd":false},{"ty":"tr","p":{"a":0,"k":[254.805,250],"ix":2},"a":{"a":0,"k":[33.231,32.25],"ix":1},"s":{"a":0,"k":[490,490],"ix":3},"r":{"a":0,"k":0,"ix":6},"o":{"a":0,"k":100,"ix":7},"sk":{"a":0,"k":0,"ix":4},"sa":{"a":0,"k":0,"ix":5},"nm":"Transform"}],"nm":"Layer 13 Outlines - Group 335","np":1,"cix":2,"bm":0,"ix":6,"mn":"ADBE Vector Group","hd":false}],"ip":0,"op":150.000006109625,"st":0,"bm":0}],"markers":[]}